Workbook
Name txtDatabaseName: "テキスト 8"
Name txtTableName: "テキスト 2"
Name txtUserName: "テキスト 4"

Sheet 表紙
B22: =TEXT(変更来歴!AT2,"yyyy年 mm月 dd日") & " " & 変更来歴!AT3 -> 2026年 06月 17日 dr1.5
C28: アメージングアクティビティ(株) | F28: HRS殿
C29: 作成 | D29: 照査 | E29: 承認 | F29: 照査 | G29: 承認

Sheet 変更来歴
A1: 文書名： | I1: 顧客名 | M1: ヒロセ電機株式会社 | X1: システム | AA1: 化学物質データ申請 | AK1: 作成者 | AN1: 古竹 | AQ1: 作成日 | AT1: =AL7 -> 46125 | AX1: 書類番号
A2: 新環境証明書システム | I2: プロジェクト | M2: 新環境証明書システム移行 | AK2: 修正者 | AN2: 古竹 | AQ2: 修正日 | AT2: 46190 | AX2: IMWF-53
A3: 画面設計書 | I3: 内容 | X3: 画面名 | AA3: 化学物質データ申請確認 | AQ3: Rev | AT3: =INDIRECT("A" & COUNTA(A7:A39) + 6) -> dr1.5
A5: 変更来歴
A6: Rev. | C6: 変更内容 | Q6: 変更・追加箇所 | AL6: 提出日 | AP6: 作成者 | AS6: 承認者 | AV6: 備考
A7: dr1.0 | C7: 新規作成 | AL7: 46125 | AP7: 古竹
A8: dr1.1 | C8: 「化学物質データ申請確認画面」シート | Q8: 化学物質データ申請確認画面の内容を日英併記に変更 | AL8: 46134 | AP8: 古竹
A9: dr1.2 | C9: 「化学物質データ申請確認画面」シート | Q9: 英語表記を現行の英語表記に変更、項目変更 | AL9: 46162 | AP9: 古竹
A10: dr1.3 | C10: 「化学物質データ申請確認画面」シート、「処理詳細」シート | Q10: ・エラーメッセージエリアを削除 ・共通ヘッダーを追加 ・処理詳細のフロー図で不要個所をグレーアウト | AL10: 46177 | AP10: 古竹
A11: dr1.4 | C11: 「画面項目」シート | Q11: ・HRSロゴとパンくずリストのリンクを押下した際の遷移先を修正 ・テーブル情報変更に伴い修正 | AL11: 46184 | AP11: 古竹
A12: dr1.5 | C12: 「化学物質データ申請確認画面」シート、「画面項目」シート、「処理詳細」シート | Q12: 課題リストの回答をもとに修正 | AL12: 46190 | AP12: 古竹

Sheet 化学物質データ申請確認画面
A1: 文書名： | I1: 顧客名 | M1: =変更来歴!M1 -> ヒロセ電機株式会社 | X1: システム | AA1: =変更来歴!AA1 -> 化学物質データ申請 | AK1: 作成者 | AN1: =変更来歴!AP7 -> 古竹 | AS1: 作成日 | AV1: =変更来歴!AL7 -> 46125 | AZ1: 書類番号
A2: intra-mart Accel Platform | I2: プロジェクト | M2: =変更来歴!M2 -> 新環境証明書システム移行 | AK2: 修正者 | AN2: =INDIRECT("変更来歴!AP" & COUNTA(変更来歴!AP7:'変更来歴'!AP39) + 6) -> 古竹 | AS2: 修正日 | AV2: =INDIRECT("変更来歴!AL" & COUNTA(変更来歴!AL7:'変更来歴'!AL39) + 6) -> 46190 | AZ2: =変更来歴!AX2 -> IMWF-53
A3: =変更来歴!A3 -> 画面設計書 | I3: 内容 | M3: =RIGHT(CELL("filename",A1),LEN(CELL("filename",A1))-FIND("]",CELL("filename",A1))) -> 化学物質データ申請確認画面 | X3: 画面名 | AA3: =MID(CELL("filename"),FIND("]",CELL("filename"))+1,LEN(CELL("filename"))) & "画面" -> 表紙画面 | AS3: Rev | AV3: =INDIRECT("変更来歴!A" & COUNTA(変更来歴!A7:'変更来歴'!A39) + 6) -> dr1.5
A5: ="画面レイアウト"&"("&MID(CELL("filename"),FIND("]",CELL("filename"))+1,LEN(CELL("filename")))&")" -> 画面レイアウト(表紙) | BB5: Rev.
B6: 1 | C6: 2 | D6: 3 | E6: 4 | F6: 5 | G6: 6 | H6: 7 | I6: 8 | J6: 9 | K6: 10 | L6: 11 | M6: 12 | N6: 13 | O6: 14 | P6: 15 | Q6: 16 | R6: 17 | S6: 18 | T6: 19 | U6: 20 | V6: 21 | W6: 22 | X6: 23 | Y6: 24 | Z6: 25 | AA6: 26 | AB6: 27 | AC6: 28 | AD6: 29 | AE6: 30 | AF6: 31 | AG6: 32 | AH6: 33 | AI6: 34 | AJ6: 35 | AK6: 36 | AL6: 37 | AM6: 38 | AN6: 39 | AO6: 40 | AP6: 41 | AQ6: 42 | AR6: 43 | AS6: 44 | AT6: 45 | AU6: 46 | AV6: 47 | AW6: 48 | AX6: 49 | AY6: 50 | AZ6: 51
C8: ホーム / 化学物質データ申請確認 | BF8: 機能仕様
BF9: 1. パンくずリストエリア
W10: 化学物質データ/Chemical substance data | BG10: 1.1 パンくずリスト
C11: 製品選択フォーム Product selection form | BH11: 以下のようにパンくずリストを表示する。
BH12: 『製品トップ > 化学物質データ申請確認』
C14: 申請した製品数: 5 件 Number of products applied: 5 products | BF14: 2.申請確認エリア
BF15: 申請内容に不備があった場合のエラーメッセージは
BF16: ポップアップで表示
E18: Items | P18: 日本語 | AB18: English
E19: Non-compliant | P19: 非適合の為、提出できません。 | AB19: We can't submit the certificate for non-compliant.
E20: Request | P20: ヒロセ営業担当へご連絡、または環境各種要求書を発行 | AB20: Please contact to Hirose sales or request on the environment data base.
E21: グレー背景 Gray background | P21: 重複した製品 | AB21: Duplicate products
E22: 赤背景 Red background | P22: システムに製品の該当なし | AB22: Products are not registered in the system.
E26: 提出先企業名 Submission_company | R26: 123456
E29: エンドユーザー End user | R29: A社
G33: 製品名 Product name | J33: CL | M33: 新製品区分 New Product Class | P33: 製品販売 状況 Product Sales Status | S33: PCN番号 PCN No | V33: RoHS証明書 RoHS Certificate | Y33: ハロゲンフリー証明書 Certificate of Halogen Free | AB33: 成分表 Product Chemical Substances Table | AE33: 高精度分析データ(ICP) Analysis Data(ICP) | AH33: SDS | AK33: chemSHERPA | AN33: SVHC調査報告書 Report of SVHC
E36: ☑ | G36: NameA | J36: CL0123- 4567-8-90 | M36: オリジナル Original | P36: 生産終了 予定品 Products to be discontinued | S36: 2024-01 | V36: YES | Y36: YES | AB36: YES | AE36: YES | AH36: YES | AK36: YES | AN36: YES
G39: NameA | J39: CL0123- 4567-8-90 | M39: オリジナル Original | P39: 生産終了 予定品 Products to be discontinued | S39: 2024-01 | V39: YES | Y39: YES | AB39: YES | AE39: YES | AH39: YES | AK39: YES | AN39: YES
E42: ☑ | G42: NameB | J42: CL0123- 4567-8-91 | M42: オリジナル (特定社) Original(Specified company) | P42: 生産終了 予定品 Products to be discontinued | S42: 2023-12 | V42: Non-complia nt | Y42: Non-complia nt | AB42: YES | AE42: YES | AH42: Request | AK42: YES | AN42: YES
E45: ☑ | G45: NameC | J45: CL0123- 4567-8-92 | M45: カスタム(他 社販売可) Custom(Can be sold by other companies) | P45: 新規設計 非推奨 New designs are not recommended | S45: - | V45: Non-complia nt | Y45: YES | AB45: YES | AE45: YES | AH45: Request | AK45: Request | AN45: Request
E48: ☑ | G48: NameD | J48: CL0123- 4567-8-93 | M48: カスタム(他 社販売可) Custom(Can be sold by other companies) | P48: 新規設計 非推奨 New designs are not recommended | S48: 2023-11 | V48: YES | Y48: Non-complia nt | AB48: YES | AE48: YES | AH48: YES | AK48: YES | AN48: YES
G51: NameF | J51: CL0123- 4567-8-95 | M51: カスタム(他 社販売不可) Custom(Cannot be sold by other companies) | P51: 販売品 Items for sales | S51: 2023-10 | V51: Request | Y51: Request | AB51: Request | AE51: Request | AH51: Request | AK51: Request | AN51: Request
G54: - | J54: CL0123- 4567-8-96 | M54: - | P54: - | S54: -
E65: 申請確認ダイアログ
E66: Application confirmation dialog
G69: 化学物質データ新規申請を行いますか
J70: (○○ 件)
E71: Do you want to apply?
J72: (○○ Items)

Sheet 画面項目
A1: 画面項目(Screen Items)
A2: 必須記入
A3: 項番 (No) | C3: 項目名(Item Name) | Q3: 初期値 (Default Value) | AB3: フォーマット (Format) | AI3: 導出元 (Source) | AR3: 備考 (Comment)
C4: エリア （Area） | J4: 項目名 (Item Name)
A5: 0 | C5: 共通ヘッダー
A6: 0.1 | J6: ヒロセ電機ロゴ | Q6: - | AR6: 「化学物質データ画面」～「化学物質データ申請完了画面」共通 ロゴを押下するとヒロセ電機HPトップページに遷移する。
A7: 1 | C7: パンくずリストエリア
A8: 1.1 | J8: パンくずリスト | Q8: - | AR8: ホーム画面: ホーム (リンクなし)
A9: 2 | C9: 申請確認エリア | Q9: -
A10: 2.1 | J10: 初期申請製品数 | Q10: 申請確認画面で表示された製品数 ※重複、製品データ該当なしの件数も含む | AI10: 申請画面のHTTPパラメータ
A11: 2.2 | J11: 申請に対するチェック結果の説明 | Q11: -
A12: 2.3 | J12: 提出先企業名 | Q12: 申請画面からフォーム送信される「提出先企業名」パラメータの値 | AI12: 申請画面のHTTPパラメータ
A13: 2.4 | J13: エンドユーザー | Q13: 申請画面からフォーム送信される「エンドユーザー」パラメータの値 | AI13: 申請画面のHTTPパラメータ
A14: 2.5 | J14: CSVダウンロードボタン | Q14: -
A15: 2.6 | J15: 申請チェックボックス | Q15: 申請可否の情報 | AI15: 処理項目：項番1参照 | AR15: ※画面表示フォーマットは「処理詳細」シートの「■A－１－７－２．製品証明書情報取得処理よりエラーハンドリングフォーマット」を参照する
A16: 2.7 | J16: 製品名 | Q16: 申請画面からフォーム送信される「製品名/CL-No」の配列パラメータの値、または、「環境証明書申請製品情報」の「製品名」の値 | AI16: 申請可能製品情報マスタ 製品名 | AR16: <表示内容>（製品名とCLコード） ①申請画面からフォーム送信される「製品名/CL-No」を基に「環境証明書申請製品情報」を取得できた場合 ・画面項目.製品名：データ「環境証明書申請製品情報」の「製品名」を表示する ・画面項目.CLコード：データ「環境証明書申請製品情報」の「CLコード」を表示する ②上記①でない場合 1）申請画面からフォーム送信される「製品名/CL-No」の配列パラメータ値が 「HrsNo形式」（数値11桁）、または、「CLコード形式」（CL9999-9999-9-99）の場合 ・画面項目.製品名："-"（ハイフン）を表示する ・画面項目.CLコード：申請画面からフォーム送信される「製品名/CL-No」の配列パラメータ値を表示する。 2）上記1）でない場合 ・画面項目.製品名：申請画面からフォーム送信される「製品名/CL-No」の配列パラメータ値を表示する。 ・画面項目.CLコード："-"（ハイフン）を表示する ※値がないときは"-"（ハイフン）を表示する。 （値がないときとはレコードなしや値がnullの場合を指す。従って、例えば値がスペースなどのときは、スペースという値があると判定）
A17: 2.8 | J17: CL（製品番号） | Q17: 申請画面からフォーム送信される「製品名/CL-No」の配列パラメータの値、または、「環境証明書申請製品情報」の「CLコード」の値 | AI17: 申請可能製品情報マスタ CLコード | AR17: <表示内容> 上記の「製品名」の「<表示内容>（製品名とCLコード）」を参照 ※画面表示フォーマットは「処理詳細」シートの「■A－１－７－２．製品証明書情報取得処理よりエラーハンドリングフォーマット」を参照する
A18: 2.9 | J18: 申請された証明書種類 | Q18: 申請画面からフォーム送信される「化学物質データ選択」配列パラメータの値 | AI18: 申請画面のHTTPパラメータ | AR18: 既存項目の「AIS」は本改修で削除
A19: 2.10 | J19: 製品毎の申請可否チェック結果 | Q19: 2.8の製品番号に対応する証明書毎のチェック結果 | AR19: ■区分値（証明書単位）のセット仕様 ・YES : 申請可能 ・Non-compliant : 申請不可 ・Request : 別途問合せしてください、の意味 ・Contact：既存の問い合わせルートでの申請に促す ■行（製品単位）のセット仕様： ・グレー背景色：重複した製品名/CL番号 ・赤背景色：システムに製品の該当なし ※画面表示フォーマットは「処理詳細」シートの「■A－１－７－２．製品証明書情報取得処理よりエラーハンドリングフォーマット」を参照する
A20: 2.11 | J20: 戻る | Q20: -
A21: 2.12 | J21: 申請 | Q21: - | AR21: ■チェックボックスが一つも選択されない場合、 「申請」ボタンは非活性となる。 ■チェックボックスが一つ以上選択さてている場合、 「申請確認ダイアログ」がポップアップで表示される。
A22: 2.13 | J22: いいえボタン | Q22: - | AR22: 申請確認ダイアログをクローズして、申請処理は実行しない。
A23: 2.14 | J23: はいボタン | Q23: - | AR23: 申請確認ダイアログをクローズする。 ※処理詳細の「Ａ－３．申請について」を参照する。 ※「申請処理」エラー時 ・入力チェックエラーが発生する場合、該当のエラーメッセージを2.19の画面項目に表示する。 ※「入力チェック」シート参照 ・処理エラーが発生する場合、message.E.F.000031で定義されているエラーメッセージを2.19の画面項目に表示する。
A24: 2.15 | J24: 申請製品数 | Q24: - | AR24: 選択された製品の件数を表示する。
Q25: -

Sheet 処理詳細
A1: 処理詳細
B3: １－１．画面初期表示について
E5: ※以下のフロー図を参照する
E70: １－１－１． | I70: 申請画面からのHTTPパラメータで製品名/CLコードリスト取得
E72: １－１－２． | I72: 製品名/CLコードより証明書の情報取得
F74: テーブル | O74: 申請テーブル
F75: 抽出条件（OR） | O75: 申請可能製品情報マスタ CLコード=入力リスト.製品名/CLコード ※1
O76: 申請可能製品情報マスタ 製品名=入力リスト.製品名/CLコード ※2
F77: ※1 入力値の形式がHRS-No（数字11桁）の場合はCLコードの形式（CL9999-9999-9-99）に変換
F78: ※2 入力値に以下の全角記号が含まれる場合は半角に変換
H79: － → -
H80: （ → (
H81: ） → )
H82: ＋ → +
H83: ＊ → *
H84: ／ → /
F86: ■１－１－２－１．申請製品情報マスタ（HrsChemicalSubstanceProduct）
F88: No | G88: 修飾子 | O88: 項目名
F89: 1 | G89: clCode | O89: CLコード
F90: 2 | G90: hrsNo | O90: HRS No
F91: 3 | G91: partNo | O91: 製品名
F92: 4 | G92: available | O92: 申請可能
F93: 5 | G93: request | O93: Request
F94: 6 | G94: nonCompliant | O94: Non-compliant
F95: 7 | G95: version | O95: バージョン
F97: ■１－１－２－２．取得した製品照明書の情報と画面表示のマッピング
E124: １－１－３． | I124: 製品名/CLコードの重複チェック
F126: ・１－１－２．で環境証明書申請製品情報を取得できた場合 | Y126: ： | Z126: 環境証明書申請製品情報の「CLコード」を基に重複チェックを実施
F127: ・１－１－２．で環境証明書申請製品情報を取得できなかった場合 | Y127: ： | Z127: 入力リスト.製品名/CLコードを基に重複チェックを実施
E130: １－１－７．申請可能チェック結果取得
F131: ■１－１－７－１．判断結果より処理について
H133: 社員と販売と代理店権限 | AL133: 代理店権限
H134: １－１－４．CLコードより一致する製品証明書の情報を取得 まで処理結果 | AL134: １－１－６．申請可能チェック結果OK | AR134: １－１－６．申請可能チェック結果NG
H135: 申請製品情報マスタに存在する | W135: すべての証明書が（Non-compliant ）申請不可 | AL135: なにもしない | AR135: なにもしない
W136: 証明書は１件以上申請可能 ※「YES : 申請可能」または「Request : 問い合わせ可否はシステムで判断できない」） | AL136: なにもしない | AR136: 「Contact」に書き直す
H137: 申請製品情報マスタに存在しない | AL137: なにもしない | AR137: なにもしない
H138: 製品が重複する | AL138: なにもしない | AR138: なにもしない
F140: ■１－１－７－２．製品証明書情報取得処理よりエラーハンドリングフォーマット
F142: 社員と販売と代理店権限
F143: １－１－４．CLコードより一致する製品証明書の情報を取得 まで処理結果 | AJ143: 背景色 | AM143: 文字列 | AR143: チェックボックス | AU143: パターン
F144: 申請製品情報マスタに存在する | U144: すべての証明書が（Non-compliant ）申請不可 | AJ144: 灰色 | AM144: Non-compliant | AR144: 表示しない | AU144: ①
U145: 申請可能（YES）の証明書がない ※「Non-compliant : 申請不可」または「Request : 問い合わせ可否はシステムで判断できない」） | AJ145: なし | AM145: Request(+)/Non-compliant(*) | AR145: 表示しない | AU145: ②
U146: 証明書は１件以上申請可能 ※「YES : 申請可能」 | AJ146: なし | AM146: YES(+)/Request(*)/Non-compliant(*) | AR146: 表示 | AU146: ③
F147: 申請製品情報マスタに存在しない | AJ147: 赤 | AM147: 空白 | AR147: 表示しない | AU147: ④
F148: CLが重複する | AJ148: 灰色 | AM148: 空白 | AR148: 表示しない | AU148: ⑤
B150: ２－１．CSVダウンロードについて
E152: ■２－１－１ダウンロードCSVファイルのフォーマット
F154: ※「ダウンロードCSVファイルについて」のシートを参照する
E156: ■２－１－２データ情報取得
F157: ※対応するデータ情報の取得について、「２－１－２．製品名/CLコードより証明書の情報取得 」を参照する
F158: ※対応するデータ情報の取得について、「２－１－５．製品名/CLコードより申請可能製品情報マスター情報取得 」を参照する
E161: ■２－１－３取得した製品証明書の情報とダウンロードCSV項目のマッピング
E188: ■２－１－４取得した製品マスターの情報と画面表示のマッピング
F190: ※別ブック「SERP110_帳票定義書_環境証明書申請製品一覧.xlsx」を参照
G191: ◆CSVヘッダーのファイル出力例と導出元
G192: ◆CSV本文のファイル出力例と導出元
B194: ３－１．申請について
E196: ※以下のフロー図を参照する
E246: ３－１－１． | I246: 申請データをinsertする処理
F248: ※処理詳細は「出力編集仕様（DB）」のシートを参照する
E250: ３－１－２． | I250: 申請CSVファイル出力
F252: ■ファイル出力例と導出元
H254: 行番号 | K254: 項目 | V254: 説明 | AF254: 導出元(Source) | BD254: 備考
H255: 1 | K255: 2018-00001 | V255: 申請番号 | AF255: 申請製品 申請ID | BD255: DB自動採番
H256: 2 | K256: "1","1","0","1","0","1","0" | V256: 申請する化学物質証明書 | AF256: HTTPリクエストパラメータの「化学物質データ選択」の配列数分ループ。 1件のパラメータについて、 RoHS適合証明書→ハロゲンフリー証明書→ICP→SDS→AIS→chemSHERPA→SVHC調査報告書 の順番で照合し、マッチした場合は"1"、アンマッチの場合は"0" ※証明書順番の情報はシステムマスタの対応するキーを参照する Key：chemicalsubstancedata.csv.sort Value：rohc,ais,halogen_free ..etc | BD256: 例： ・RoHS、ハロゲンフリ、証明書、ICP、SDS、AIS、chemSHERPA、SVHC調査報告書を申請する場合、「RoHS適合証明書→ハロゲンフリー証明書→ICP→SDS→AIS→chemSHERPA→SVHC調査報告書」とぴったりマッチするため、「"1","1","1","1","1","1","1","1"」になります。 ・RoHS、ICP、AIS、chemSHERPAを申請する場合、「RoHS適合証明書→ハロゲンフリー証明書→ICP→SDS→AIS→chemSHERPA→SVHC調査報告書」とマッチして、太字の項目がマッチしないため、「"1","0","0","1","0","1","1","0"」になります。
H257: 3 | K257: CL0222-4567-8-90 | V257: 申請したCL番号 | AF257: 画面.CLコードリスト ※画面で選択されたCLコードが対象となる
H258: 4 | K258: CL0222-4567-8-91
H259: 5 | K259: CL0222-4567-8-92
H260: ： | K260: ：
E263: 4－1－1． | I263: 環境証明書申請完了お知らせメール送信
F264: ①送信トリガー
F265: 送信トリガー | O265: 申請確認ダイアログで「はい」ボタン押下時
F267: ②メールヘッダー定義
F268: 項目 | O268: 設定内容
F269: From | O269: GM_no-reply@hirose.com
F270: To | O270: user@mail.com
F271: 送信トリガー | O271: <HRS:20XX-000XXX> Chemical substance data application completion/化学物質データ申請完了
F274: 「SEML030 環境証明書申請完了お知らせメール」を送信する。
F275: また、申請者のサイト言語(HrsCustomer.sessionLanguage)に対応するメールテンプレートを使用する。

Sheet 出力編集仕様
A1: 出力編集仕様
A2: 化学物質データの環境証明書申請内容をデータベースに登録する。
A5: タイプ | J5: 証明書申請テーブル, 証明書申請入力テーブル
A6: 説明 | J6: 申請ボタンを押下する時 INSERT（UPDATEは発生しない） | AD6: 備考
A8: No | B8: 修飾子
B9: 申請テーブル
A10: 1 | B10: 受付番号 | J10: 暦年と5桁の追番の間にハイフン（例：2018-00001） ※追番はhybrisのGeneratorの機構で生成する値（hrsChemicalSubstanceAppNoSeq） | AD10: 画面項目の2.8毎に処理
A11: 2 | B11: 申請者アカウントID | J11: ログインユーザのHrsCustomer.uid
A12: 3 | B12: 申請日時 | J12: システムの日付
A13: 4 | B13: ステータス | J13: 画面.提出先企業名 | AD13: 画面項目の2.3
A14: 5 | B14: エンドユーザ名 | J14: 画面.エンドユーザ | AD14: 画面項目の2.4
A15: 6 | B15: ステータス | J15: 未処理（ChemicalSubstanceStatus.unprocessed） | AD15: 申請ファイル取り込みバッチで更新できる
A16: 7 | B16: 有効期限 | J16: - | AD16: 申請ファイル取り込みバッチで更新する
A17: 8 | B17: ファイルサイズ | J17: - | AD17: 同上
A18: 9 | B18: フォルダ数 | J18: - | AD18: 同上
A19: 10 | B19: ファイル数 | J19: - | AD19: 同上
A22: 備考
A23: ※1 | C23: 登録対象の言語は画面で選択可能な7言語（英語、日本語、韓国語、中国語、フランス語、ドイツ語、ロシア語）
C24: 基本的に、登録元の「製品マスター情報.新製品区分」にはGPDMから連携された言語のみ値が設定されている想定
C25: 値が設定されていない言語の場合は、英語の値（フォールバック値）を設定（該当言語の内容に翻訳などはしない）

Sheet ダウンロードCSVファイルについて
A1: ダウンロードCSV
A2: 化学物質データ申請確認画面で「CSVダウンロード」ボタンを押下すると該当するファイルを生成する
B5: ◆出力項目について
C7: ■RoHS、ハロゲンフリー、成分表、JAMP、SDS、chemSHERPA、SVHC調査報告書を申請する場合
D9: 例：
D10: Part No | K10: CLコード | R10: New Product Class | Y10: Product Sales Status Class | AF10: PCN No | AM10: CL check | AT10: Name of company to be submitted | BA10: End customer | BH10: Certificate of RoHS Conformity | BO10: Certificate of Halogen Free | BV10: Product Chemical Substances Table | CC10: JAMP AIS | CJ10: SDS | CQ10: chemSHERPA | CX10: SVHC
D11: NameA | K11: CL0123-4567-8-90 | R11: オリジナル | Y11: 生産終了予定品 | AF11: 2024-01 | AT11: B社 | BA11: A社 | BH11: YES | BO11: YES | BV11: YES | CC11: YES | CJ11: YES | CQ11: YES | CX11: YES
D12: NameA | K12: CL0123-4567-8-90 | R12: オリジナル | Y12: 生産終了予定品 | AF12: 2024-01 | AM12: 重複
D13: NameB | K13: CL0123-4567-8-91 | R13: オリジナル(特定社) | Y13: 生産終了品 | AF13: 2023-12 | AT13: B社 | BA13: A社 | BH13: Non-compliant | BO13: Non-compliant | BV13: YES | CC13: YES | CJ13: Request | CQ13: YES | CX13: YES
D14: NameC | K14: CL0123-4567-8-92 | R14: カスタム(他社販売可) | Y14: 新規設計非推奨 | AF14: - | AT14: B社 | BA14: A社 | BH14: YES | BO14: YES | BV14: YES | CC14: YES | CJ14: Request | CQ14: Request | CX14: Request
D15: NameE | K15: CL0123-4567-8-94 | R15: カスタム(他社販売不可) | Y15: 販売品 | AF15: - | AT15: B社 | BA15: A社 | BH15: YES | BO15: YES | BV15: YES | CC15: YES | CJ15: YES | CQ15: YES | CX15: YES
D16: - | K16: CL0123-4567-8-96 | R16: - | Y16: - | AF16: - | AM16: 該当なし | AT16: B社 | BA16: A社 | BH16: Request | BO16: Request | BV16: Request | CC16: Request | CJ16: Request | CQ16: Request | CX16: Request
C19: ■RoHS、ハロゲンフリー、成分表、JAMPを申請する場合
D21: 例：
D22: Part No | K22: CLコード | R22: New Product Class | Y22: Product Sales Status Class | AF22: PCN No | AM22: CL check | AT22: Name of company to be submitted | BA22: End customer | BH22: Certificate of RoHS Conformity | BO22: Certificate of Halogen Free | BV22: Product Chemical Substances Table | CC22: JAMP AIS
D23: NameA | K23: CL0123-4567-8-90 | R23: オリジナル | Y23: 生産終了予定品 | AF23: 2024-01 | AT23: B社 | BA23: A社 | BH23: YES | BO23: YES | BV23: YES | CC23: YES
D24: NameA | K24: CL0123-4567-8-90 | R24: オリジナル | Y24: 生産終了予定品 | AF24: 2024-01 | AM24: 重複
D25: NameB | K25: CL0123-4567-8-91 | R25: オリジナル(特定社) | Y25: 生産終了品 | AF25: 2023-12 | AT25: B社 | BA25: A社 | BH25: Non-compliant | BO25: Non-compliant | BV25: YES | CC25: YES
D26: NameC | K26: CL0123-4567-8-92 | R26: カスタム(他社販売可) | Y26: 新規設計非推奨 | AF26: - | AT26: B社 | BA26: A社 | BH26: YES | BO26: YES | BV26: YES | CC26: YES
D27: NameE | K27: CL0123-4567-8-94 | R27: カスタム(他社販売不可) | Y27: 販売品 | AF27: - | AT27: B社 | BA27: A社 | BH27: YES | BO27: YES | BV27: YES | CC27: YES
D28: - | K28: CL0123-4567-8-96 | R28: - | Y28: - | AF28: - | AM28: 該当なし | AT28: B社 | BA28: A社 | BH28: Request | BO28: Request | BV28: Request | CC28: Request
B30: ※ | C30: ①該当するCSVの内容は画面で表示されるCL製品一覧の項目＋上記の点線で囲まれた項目である。
C31: ②画面でチェックボックスを選択してないデータ、重複したデータまたはNon-compliantのデータもすべて出力される。
C32: ③製品名の昇順、CLコードの昇順（値がない場合は末尾）にて出力する（当画面の表示順と同じ仕様にする）
C33: ④画面から引き渡されているCLコード、提出先企業名、エンドユーザーなどの項目以外について（詳細は別ブック「SERP110_帳票定義書_環境証明書申請製品一覧.xlsx」を参照）、「CSV DOWNLOAD」ボタン押下時に再度出力内容を取得している。

Sheet 選択画面
A1: 文書名： | I1: 顧客名 | M1: =変更来歴!M1 -> ヒロセ電機株式会社 | X1: システム | AA1: =変更来歴!AA1 -> 化学物質データ申請 | AK1: 作成者 | AN1: =変更来歴!AP7 -> 古竹 | AS1: 作成日 | AV1: =変更来歴!AL7 -> 46125 | AZ1: 書類番号
A2: intra-mart Accel Platform | I2: プロジェクト | M2: =変更来歴!M2 -> 新環境証明書システム移行 | AK2: 修正者 | AN2: =INDIRECT("変更来歴!AP" & COUNTA(変更来歴!AP7:'変更来歴'!AP39) + 6) -> 古竹 | AS2: 修正日 | AV2: =INDIRECT("変更来歴!AL" & COUNTA(変更来歴!AL7:'変更来歴'!AL39) + 6) -> 46190 | AZ2: =変更来歴!AX2 -> IMWF-53
A3: =変更来歴!A3 -> 画面設計書 | I3: 内容 | M3: =RIGHT(CELL("filename",A1),LEN(CELL("filename",A1))-FIND("]",CELL("filename",A1))) -> 選択画面 | X3: 画面名 | AA3: =MID(CELL("filename"),FIND("]",CELL("filename"))+1,LEN(CELL("filename"))) & "画面" -> 表紙画面 | AS3: Rev | AV3: =INDIRECT("変更来歴!A" & COUNTA(変更来歴!A7:'変更来歴'!A39) + 6) -> dr1.5
A5: ="画面レイアウト"&"("&MID(CELL("filename"),FIND("]",CELL("filename"))+1,LEN(CELL("filename")))&")" -> 画面レイアウト(表紙) | BB5: Rev.
B6: 1 | C6: 2 | D6: 3 | E6: 4 | F6: 5 | G6: 6 | H6: 7 | I6: 8 | J6: 9 | K6: 10 | L6: 11 | M6: 12 | N6: 13 | O6: 14 | P6: 15 | Q6: 16 | R6: 17 | S6: 18 | T6: 19 | U6: 20 | V6: 21 | W6: 22 | X6: 23 | Y6: 24 | Z6: 25 | AA6: 26 | AB6: 27 | AC6: 28 | AD6: 29 | AE6: 30 | AF6: 31 | AG6: 32 | AH6: 33 | AI6: 34 | AJ6: 35 | AK6: 36 | AL6: 37 | AM6: 38 | AN6: 39 | AO6: 40 | AP6: 41 | AQ6: 42 | AR6: 43 | AS6: 44 | AT6: 45 | AU6: 46 | AV6: 47 | AW6: 48 | AX6: 49 | AY6: 50 | AZ6: 51
B7: 単価上申(円販売一般品) | N7: 案件番号： | R7: CD-1234567
C10: Step １： 起票区分を選択してください
D12: ◎ | E12: 販売単価上申書
B13: 1 | C13: 2 | G13: 6 | H13: 7 | I13: 8 | J13: 9 | K13: 10 | L13: 11 | M13: 12 | N13: 13 | O13: 14 | P13: 15 | Q13: 16 | R13: 17 | S13: 18 | T13: 19 | U13: 20 | V13: 21 | W13: 22 | X13: 23 | Y13: 24 | Z13: 25 | AA13: 26 | AB13: 27 | AC13: 28 | AD13: 29 | AE13: 30 | AF13: 31 | AG13: 32 | AH13: 33 | AI13: 34 | AJ13: 35 | AK13: 36 | AL13: 37 | AM13: 38 | AN13: 39 | AO13: 40 | AQ13: 41 | AR13: 42 | AS13: 43 | AT13: 44 | AU13: 45 | AV13: 46 | AW13: 47
B14: 2 | C14: Step ２： 一般品またはカスタムのいずれかを選択してください
D16: ○ | E16: 一般品
B17: 3
D18: ○ | E18: カスタム
C20: Step ３： 円販売または外貨販売のいずれかを選択してください
D22: ○ | E22: 円販売
B23: 2
D24: ○ | E24: 外貨販売
B36: 4
B38: 36
B39: 37

Sheet 円(PPM)
A1: 文書名： | I1: 顧客名 | M1: =変更来歴!M1 -> ヒロセ電機株式会社 | X1: システム | AA1: =変更来歴!AA1 -> 化学物質データ申請 | AK1: 作成者 | AN1: =変更来歴!AP7 -> 古竹 | AS1: 作成日 | AV1: =変更来歴!AL7 -> 46125 | AZ1: 書類番号
A2: intra-mart Accel Platform | I2: プロジェクト | M2: =変更来歴!M2 -> 新環境証明書システム移行 | AK2: 修正者 | AN2: =INDIRECT("変更来歴!AP" & COUNTA(変更来歴!AP7:'変更来歴'!AP39) + 6) -> 古竹 | AS2: 修正日 | AV2: =INDIRECT("変更来歴!AL" & COUNTA(変更来歴!AL7:'変更来歴'!AL39) + 6) -> 46190 | AZ2: =変更来歴!AX2 -> IMWF-53
A3: =変更来歴!A3 -> 画面設計書 | I3: 内容 | M3: =RIGHT(CELL("filename",A1),LEN(CELL("filename",A1))-FIND("]",CELL("filename",A1))) -> 円(PPM) | X3: 画面名 | AA3: =MID(CELL("filename"),FIND("]",CELL("filename"))+1,LEN(CELL("filename"))) & "画面" -> 表紙画面 | AS3: Rev | AV3: =INDIRECT("変更来歴!A" & COUNTA(変更来歴!A7:'変更来歴'!A39) + 6) -> dr1.5
A5: ="画面レイアウト"&"("&MID(CELL("filename"),FIND("]",CELL("filename"))+1,LEN(CELL("filename")))&")" -> 画面レイアウト(表紙) | BB5: Rev.
B6: 1 | C6: 2 | D6: 3 | E6: 4 | F6: 5 | G6: 6 | H6: 7 | I6: 8 | J6: 9 | K6: 10 | L6: 11 | M6: 12 | N6: 13 | O6: 14 | P6: 15 | Q6: 16 | R6: 17 | S6: 18 | T6: 19 | U6: 20 | V6: 21 | W6: 22 | X6: 23 | Y6: 24 | Z6: 25 | AA6: 26 | AB6: 27 | AC6: 28 | AD6: 29 | AE6: 30 | AF6: 31 | AG6: 32 | AH6: 33 | AI6: 34 | AJ6: 35 | AK6: 36 | AL6: 37 | AM6: 38 | AN6: 39 | AO6: 40 | AP6: 41 | AQ6: 42 | AR6: 43 | AS6: 44 | AT6: 45 | AU6: 46 | AV6: 47 | AW6: 48 | AX6: 49 | AY6: 50 | AZ6: 51
B7: 単価上申(円販売一般品) | N7: 案件番号： | R7: SA-PR123456
E8: 過去の申請から内容コピー
C10: 起票日 | F10: ： | H10: 2022/09/29
C11: 所属 | F11: ： | H11: ヒロセ電機株式会社/管理本部/ＩＴ統括部/情報システム企画課
C12: 社員番号 | F12: ： | H12: hirose | L12: 氏名 ： | O12: システム担当者
B13: 1 | C13: 2 | D13: 3 | E13: 4 | F13: 5 | G13: 6 | H13: 7 | I13: 8 | J13: 9 | K13: 10 | L13: 11 | M13: 12 | N13: 13 | O13: 14 | P13: 15 | Q13: 16 | R13: 17 | S13: 18 | T13: 19 | U13: 20 | V13: 21 | W13: 22 | X13: 23 | Y13: 24 | Z13: 25 | AA13: 26 | AB13: 27 | AC13: 28 | AD13: 29 | AE13: 30 | AF13: 31 | AG13: 32 | AH13: 33 | AI13: 34 | AJ13: 35 | AK13: 36 | AL13: 37 | AM13: 38 | AN13: 39 | AO13: 40 | AQ13: 41 | AR13: 42 | AS13: 43 | AT13: 44 | AU13: 45 | AV13: 46 | AW13: 47
B14: 2 | C14: 申請内容
C16: 起票区分 | H16: ◎ 単価上申書
B17: 3 | C17: タイトル*
C18: 得意先コード | T18: 得意先名* | AK18: 客先担当者名
C19: 案件種類* | P19: ▼ | T19: 希望承認期限* | Y19: 2022/9/29
C20: 口銭率 | L20: ☑ 口銭申請有り
B23: 2 | C23: プロジェクト情報
C25: 工事金額 | O25: 万円/月 | T25: 継続期間* | AG25: ヵ月 | AK25: 総工事金額 | AX25: 万円
C26: MFC PJ番号 | R26: MFC OPPORTUNITY番号
C27: 大分類* | H27: 大分類A | P27: ▼ | T27: 中分類* | Y27: 中分類B | AG27: ▼ | AK27: 機種* | AP27: 機種A | AX27: ▼
C28: 量産時期* | T28: 平均生産予定数量 | AG28: /月 | AK28: 競合名 | AX28: ▼
C29: 申請理由* | AX29: ▲
AX30: ▼
C31: 値引補填工事 | H31: 値引きしなければならない理由を記載してください | AX31: ▲
AX32: ▼
C33: 備考欄 | AX33: ▲
AX34: ▼
B37: 5 | C37: 申請価格入力 | AV37: 通貨：JPY
C39: 1行目の[貢献率]の桁数が異常です。入力内容を確認して下さい。
D40: 原計タイプ* | H40: ○ 技術原計 ◎ PPM原計 ○ コリア原計
B41: 6 | C41: No | D41: CL | H41: 品名* | N41: 形* | R41: 月間数量* | V41: 得意先要求 | Z41: 従来価格* | AD41: 申請価格* | AH41: PPM直接コスト* | AM41: 代理店売価 | AQ41: ピン@ | AT41: 競合名 | AX41: 備考
B42: 7 | V42: 価格
B43: 8 | C43: 1 | D43: 1130511471 | H43: RP17-13RA-12SD(71) | N43: R | Q43: ▼ | R43: 5000 | V43: 122.5 | Z43: 125 | AD43: 124 | AH43: 94.52 | AM43: 125 | AQ43: 10.3 | AT43: SMK
B44: 9 | C44: 2 | D44: 1135042200 | H44: RP34-8R-3PDL | N44: R | Q44: ▼ | R44: 5000 | V44: 39 | Z44: 40 | AD44: 40 | AH44: 36.89 | AM44: 41 | AQ44: 12.3 | AT44: 中国
B45: 10
B46: 11
B47: 12
B48: 13
B49: 14
B50: 15 | C50: ＋ 追加 ← 挿入 － 削除 ↑ 上へ ↓ 下へ
B51: 16
B52: 17
B54: 18
B55: 20 | C55: 承認者確認用 | AV55: 通貨：JPY
B57: 21 | C57: No | D57: 形 | F57: CL | J57: 品名 | P57: 原計タイプ | T57: 数量pcs/月 | X57: コスト | AB57: 得意先要求価格 | AG57: 従来価格 | AK57: 申請価格 | AO57: 貢献率 | AS57: 値引き率 | AW57: 代理店売価 | BA57: 代理店粗利率 | BE57: ピン@ | BH57: 競合名 | BL57: 備考
B58: 22 | C58: 1 | D58: =N43 -> R | F58: =D43 -> 1130511471 | J58: =H43 -> RP17-13RA-12SD(71) | P58: PPM原計 | T58: =R43 -> 5000 | X58: =AH43 -> 94.52 | AB58: =V43 -> 122.5 | AG58: =Z43 -> 125 | AK58: =AD43 -> 124 | AO58: =1-X58/AK58 -> 0.23774194 | AS58: =(AK58-AG58)/AG58 -> -0.008 | BA58: =1-(AD43/AM43) -> 0.008 | BE58: =AQ43 -> 10.3 | BH58: =AT43 -> SMK
B59: 23 | C59: 2 | D59: =N44 -> R | F59: =D44 -> 1135042200 | J59: =H44 -> RP34-8R-3PDL | P59: PPM原計 | T59: =R44 -> 5000 | X59: =AH44 -> 36.89 | AB59: =V44 -> 39 | AG59: =Z44 -> 40 | AK59: =AD44 -> 40 | AO59: =1-X59/AK59 -> 0.07775 | AS59: =(AK59-AG59)/AG59 -> 0 | BA59: =1-(AD44/AM44) -> 0.024390244 | BE59: =AQ44 -> 12.3 | BH59: =AT44 -> 中国
B60: 20 | C60: 形小計
B61: 24 | D61: 形 | AB61: 売上 | AG61: コスト合計 | AK61: 貢献額 | AO61: 貢献率 | AS61: 値引き率 | AW61: 値引き額 | BA61: 値引き前売上
B62: 25 | C62: 1 | D62: R | AB62: =SUMPRODUCT($T$58:$W$59,$AK$58:$AN$59) -> 820000 | AG62: =SUM($X$58:$AA$59) -> 131.41 | AK62: =AB62-SUMPRODUCT($T$58:$W$59,$X$58:$AA$59) -> 162950 | AO62: =$AK62/$AB62 -> 0.19871951 | AS62: =AW62/($AB62-AW62) -> -0.0060606061 | AW62: =$T$58*($AK$58-$AG$58)+$T$59*($AK$59-$AG$59) -> -5000 | BA62: =SUMPRODUCT($T$58:$W$59,$AG$58:$AJ$59) -> 825000
B63: 20 | C63: 総合計
B64: 24 | AB64: 売上 | AG64: コスト合計 | AK64: 貢献額 | AO64: 貢献率 | AS64: 値引き率 | AW64: 値引き額 | BA64: 値引き前売上
B65: 25 | AB65: =SUMPRODUCT($T$58:$W$59,$AK$58:$AN$59) -> 820000 | AG65: =SUM($X$58:$AA$59) -> 131.41 | AK65: =AB65-SUMPRODUCT($T$58:$W$59,$X$58:$AA$59) -> 162950 | AO65: =$AK65/$AB65 -> 0.19871951 | AS65: =AW65/($AB65-AW65) -> -0.0060606061 | AW65: =$T$58*($AK$58-$AG$58)+$T$59*($AK$59-$AG$59) -> -5000 | BA65: =SUMPRODUCT($T$58:$W$59,$AG$58:$AJ$59) -> 825000
B66: 27
B67: 28
B68: 29
B70: 31
C71: 添付書類
D74: ファイル名 | R74: サイズ | V74: クリア
D75: ファイル001.xlsx | R75: 102 KB
B77: 35 | BB77: r.1.1
B78: 35 | C78: 承認者設定
B79: 35 | D79: 承認ルートは必要に応じて、「承認者の追加」をクリックして入力欄を増やしてください。 設定した承認ルートは、設定した承認者の上から順に回送されます。 最終承認者は、一番下に設定してください。
B80: 35
D82: 承認者* | H82: 10637000 | P82: ▼ | R82: 古川 福待 | AB82: コメント
H83: ヒロセ電機株式会社/管理本部/ＩＴ統括部/情報システム企画課
B86: 35 | C86: ＋ 承認者の追加
D88: 承認者* | H88: 10347008 | P88: ▼ | R88: 関 博一 | W88: 部長 | AB88: コメント入力
H89: ヒロセ電機株式会社/管理本部/ＩＴ統括部
B92: 35 | C92: ＋ 承認者の追加
B93: 35
B94: 35 | C94: 確認者設定
D96: 確認者一覧
H97: 確認者名 | Q97: 部門 | AL97: クリア
H98: 志村 亜里沙 | Q98: ヒロセ電機株式会社/管理本部/ＩＴ統括部/情報システム企画課
H99: 出水 瞳 | Q99: ヒロセ電機株式会社/管理本部/ＩＴ統括部/情報システム企画課
H100: 松澤 朱海 | Q100: ヒロセ電機株式会社/管理本部/ＩＴ統括部/情報システム企画課
B103: 36
B104: 37

Sheet 円(技術原計)
A1: 文書名： | I1: 顧客名 | M1: =変更来歴!M1 -> ヒロセ電機株式会社 | X1: システム | AA1: =変更来歴!AA1 -> 化学物質データ申請 | AK1: 作成者 | AN1: =変更来歴!AP7 -> 古竹 | AS1: 作成日 | AV1: =変更来歴!AL7 -> 46125 | AZ1: 書類番号
A2: intra-mart Accel Platform | I2: プロジェクト | M2: =変更来歴!M2 -> 新環境証明書システム移行 | AK2: 修正者 | AN2: =INDIRECT("変更来歴!AP" & COUNTA(変更来歴!AP7:'変更来歴'!AP39) + 6) -> 古竹 | AS2: 修正日 | AV2: =INDIRECT("変更来歴!AL" & COUNTA(変更来歴!AL7:'変更来歴'!AL39) + 6) -> 46190 | AZ2: =変更来歴!AX2 -> IMWF-53
A3: =変更来歴!A3 -> 画面設計書 | I3: 内容 | M3: =RIGHT(CELL("filename",A1),LEN(CELL("filename",A1))-FIND("]",CELL("filename",A1))) -> 円(技術原計) | X3: 画面名 | AA3: =MID(CELL("filename"),FIND("]",CELL("filename"))+1,LEN(CELL("filename"))) & "画面" -> 表紙画面 | AS3: Rev | AV3: =INDIRECT("変更来歴!A" & COUNTA(変更来歴!A7:'変更来歴'!A39) + 6) -> dr1.5
A5: ="画面レイアウト"&"("&MID(CELL("filename"),FIND("]",CELL("filename"))+1,LEN(CELL("filename")))&")" -> 画面レイアウト(表紙) | BB5: Rev.
B6: 1 | C6: 2 | D6: 3 | E6: 4 | F6: 5 | G6: 6 | H6: 7 | I6: 8 | J6: 9 | K6: 10 | L6: 11 | M6: 12 | N6: 13 | O6: 14 | P6: 15 | Q6: 16 | R6: 17 | S6: 18 | T6: 19 | U6: 20 | V6: 21 | W6: 22 | X6: 23 | Y6: 24 | Z6: 25 | AA6: 26 | AB6: 27 | AC6: 28 | AD6: 29 | AE6: 30 | AF6: 31 | AG6: 32 | AH6: 33 | AI6: 34 | AJ6: 35 | AK6: 36 | AL6: 37 | AM6: 38 | AN6: 39 | AO6: 40 | AP6: 41 | AQ6: 42 | AR6: 43 | AS6: 44 | AT6: 45 | AU6: 46 | AV6: 47 | AW6: 48 | AX6: 49 | AY6: 50 | AZ6: 51
B7: 単価上申(円販売一般品) | N7: 案件番号： | R7: SA-PR123456
E8: 過去の申請から内容コピー
C10: 起票日 | F10: ： | H10: 2022/09/29
C11: 所属 | F11: ： | H11: ヒロセ電機株式会社/管理本部/ＩＴ統括部/情報システム企画課
C12: 社員番号 | F12: ： | H12: hirose | L12: 氏名 ： | O12: システム担当者
B13: 1 | C13: 2 | D13: 3 | E13: 4 | F13: 5 | G13: 6 | H13: 7 | I13: 8 | J13: 9 | K13: 10 | L13: 11 | M13: 12 | N13: 13 | O13: 14 | P13: 15 | Q13: 16 | R13: 17 | S13: 18 | T13: 19 | U13: 20 | V13: 21 | W13: 22 | X13: 23 | Y13: 24 | Z13: 25 | AA13: 26 | AB13: 27 | AC13: 28 | AD13: 29 | AE13: 30 | AF13: 31 | AG13: 32 | AH13: 33 | AI13: 34 | AJ13: 35 | AK13: 36 | AL13: 37 | AM13: 38 | AN13: 39 | AO13: 40 | AQ13: 41 | AR13: 42 | AS13: 43 | AT13: 44 | AU13: 45 | AV13: 46 | AW13: 47
B14: 2 | C14: 申請内容
C16: 起票区分 | H16: ◎ 単価上申書
B17: 3 | C17: タイトル*
C18: 得意先コード | T18: 得意先名* | AK18: 客先担当者名
C19: 案件種類* | P19: ▼ | T19: 希望承認期限* | Y19: 2022/9/29
C20: 口銭率 | L20: ☑ 口銭申請有り
B23: 2 | C23: プロジェクト情報
C25: 工事金額 | O25: 万円/月 | T25: 継続期間* | AG25: ヵ月 | AK25: 総工事金額 | AX25: 万円
C26: MFC PJ番号 | R26: MFC OPPORTUNITY番号
C27: 大分類* | H27: 大分類A | P27: ▼ | T27: 中分類* | Y27: 中分類B | AG27: ▼ | AK27: 機種* | AP27: 機種A | AX27: ▼
C28: 量産時期* | T28: 平均生産予定数量 | AG28: /月 | AK28: 競合名 | AX28: ▼
C29: 申請理由* | AX29: ▲
AX30: ▼
C31: 値引補填工事 | H31: 値引きしなければならない理由を記載してください | AX31: ▲
AX32: ▼
C33: 備考欄 | AX33: ▲
AX34: ▼
B36: 4
B37: 5 | C37: 申請価格入力 | AV37: 通貨：JPY
D39: 原計タイプ* | H39: ◎ 技術原計 ○ PPM原計 ○ コリア原計
B40: 6 | C40: No | D40: CL | H40: 品名* | N40: 形* | R40: 月間数量* | V40: 得意先要求 | Z40: 従来価格* | AD40: 申請価格* | AH40: 製造原価* | AM40: 総原価* | AQ40: 代理店売価 | AU40: ピン@ | AX40: 競合名 | BB40: 備考
B41: 7 | V41: 価格
B42: 8 | C42: 1 | D42: 1250103874 | H42: HR25-9TP-16P(74) | N42: R | Q42: ▼ | R42: 1000 | V42: 980 | Z42: 1610 | AD42: 1035 | AH42: 510.27 | AM42: 796.03 | AU42: 64.7 | AX42: サンウー
B43: 9 | C43: 2 | D43: 1250109471 | H43: HR25-9TR-16S(71) | N43: R | Q43: ▼ | R43: 500 | V43: 500 | Z43: 794 | AD43: 630 | AH43: 247.92 | AM43: 483.47 | AU43: 39.4 | AX43: サンウー
B44: 10
B45: 11
B46: 12
B47: 13
B48: 14
B49: 15 | C49: ＋ 追加 ← 挿入 － 削除 ↑ 上へ ↓ 下へ
B50: 16
B51: 17
B53: 18
B54: 20 | C54: 承認者確認用 | AV54: 通貨：JPY
B56: 21 | C56: No | D56: 形 | F56: CL | J56: 品名 | P56: 原計タイプ | T56: 数量pcs/月 | X56: 総原価 | AB56: 得意先要求価格 | AG56: 従来価格 | AK56: 申請価格 | AO56: 総原価利益率 | AS56: 値引き率 | AW56: 代理店売価 | BA56: 代理店粗利率 | BE56: ピン@ | BH56: 競合名 | BL56: 備考
B57: 22 | C57: 1 | D57: =N42 -> R | F57: =D42 -> 1250103874 | J57: =H42 -> HR25-9TP-16P(74) | P57: 技術原計 | T57: =R42 -> 1000 | X57: =AH42 -> 510.27 | AB57: =V42 -> 980 | AG57: =Z42 -> 1610 | AK57: =AD42 -> 1035 | AO57: =AD42/AM42-1 -> 0.30020225 | AS57: =(AK57-AG57)/AG57 -> -0.35714286 | BA57: =IFERROR(1-(AD42/AQ42),"") | BE57: =AU42 -> 64.7 | BH57: =AX42 -> サンウー
B58: 23 | C58: 2 | D58: =N43 -> R | F58: =D43 -> 1250109471 | J58: =H43 -> HR25-9TR-16S(71) | P58: 技術原計 | T58: =R43 -> 500 | X58: =AH43 -> 247.92 | AB58: =V43 -> 500 | AG58: =Z43 -> 794 | AK58: =AD43 -> 630 | AO58: =AD43/AM43-1 -> 0.30307982 | AS58: =(AK58-AG58)/AG58 -> -0.20654912 | BA58: =IFERROR(1-(AD43/AQ43),"") | BE58: =AU43 -> 39.4 | BH58: =AX43 -> サンウー
B59: 20 | C59: 形小計
B60: 24 | D60: 形 | AB60: 売上 | AG60: 総原価合計 | AK60: 総原価利益額 | AO60: 総原価利益率 | AS60: 値引き率 | AW60: 値引き額 | BA60: 値引き前売上
B61: 25 | C61: 1 | D61: R | AB61: =SUMPRODUCT($T$57:$W$58,$AK$57:$AN$58) -> 1350000 | AG61: =SUM(AM$42:AP$43) -> 1279.5 | AK61: =$AB61-SUMPRODUCT($R$42:$U$43,$AM$42:$AP$43) -> 312235 | AO61: =$AK61/($AB61-$AK61) -> 0.30087255 | AS61: =AW61/($AB61-AW61) -> -0.32735426 | AW61: =$T$57*($AK$57-$AG$57)+$T$58*($AK$58-$AG$58) -> -657000 | BA61: =SUMPRODUCT($T$57:$W$58,$AG$57:$AJ$58) -> 2007000
B62: 20 | C62: 総合計
B63: 24 | AB63: 売上 | AG63: 総原価合計 | AK63: 総原価利益額 | AO63: 総原価利益率 | AS63: 値引き率 | AW63: 値引き額 | BA63: 値引き前売上
B64: 25 | AB64: =SUMPRODUCT($T$57:$W$58,$AK$57:$AN$58) -> 1350000 | AG64: =SUM(AM$42:AP$43) -> 1279.5 | AK64: =$AB64-SUMPRODUCT($R$42:$U$43,$AM$42:$AP$43) -> 312235 | AO64: =$AK64/($AB64-$AK64) -> 0.30087255 | AS64: =AW64/($AB64-AW64) -> -0.32735426 | AW64: =$T$57*($AK$57-$AG$57)+$T$58*($AK$58-$AG$58) -> -657000 | BA64: =SUMPRODUCT($T$57:$W$58,$AG$57:$AJ$58) -> 2007000
B65: 26
B66: 27
B67: 28
B68: 29
B70: 31
C71: 添付書類
D74: ファイル名 | R74: サイズ | V74: クリア
D75: ファイル001.xlsx | R75: 102 KB
B77: 34
B78: 35 | C78: 承認者設定
B79: 35 | D79: 承認ルートは必要に応じて、「承認者の追加」をクリックして入力欄を増やしてください。 設定した承認ルートは、設定した承認者の上から順に回送されます。 最終承認者は、一番下に設定してください。
B80: 35
D82: 承認者* | H82: 10637000 | P82: ▼ | R82: 古川 福待 | AB82: コメント
H83: ヒロセ電機株式会社/管理本部/ＩＴ統括部/情報システム企画課
B86: 35 | C86: ＋ 承認者の追加
D88: 承認者* | H88: 10347008 | P88: ▼ | R88: 関 博一 | W88: 部長 | AB88: コメント入力
H89: ヒロセ電機株式会社/管理本部/ＩＴ統括部
B92: 35 | C92: ＋ 承認者の追加
B93: 35
B94: 35 | C94: 確認者設定
D96: 確認者一覧
H97: 確認者名 | Q97: 部門 | AL97: クリア
H98: 志村 亜里沙 | Q98: ヒロセ電機株式会社/管理本部/ＩＴ統括部/情報システム企画課
H99: 出水 瞳 | Q99: ヒロセ電機株式会社/管理本部/ＩＴ統括部/情報システム企画課
H100: 松澤 朱海 | Q100: ヒロセ電機株式会社/管理本部/ＩＴ統括部/情報システム企画課
B103: 36
B104: 37

Sheet 円(コリア原計)
A1: 文書名： | I1: 顧客名 | M1: =変更来歴!M1 -> ヒロセ電機株式会社 | X1: システム | AA1: =変更来歴!AA1 -> 化学物質データ申請 | AK1: 作成者 | AN1: =変更来歴!AP7 -> 古竹 | AS1: 作成日 | AV1: =変更来歴!AL7 -> 46125 | AZ1: 書類番号
A2: intra-mart Accel Platform | I2: プロジェクト | M2: =変更来歴!M2 -> 新環境証明書システム移行 | AK2: 修正者 | AN2: =INDIRECT("変更来歴!AP" & COUNTA(変更来歴!AP7:'変更来歴'!AP39) + 6) -> 古竹 | AS2: 修正日 | AV2: =INDIRECT("変更来歴!AL" & COUNTA(変更来歴!AL7:'変更来歴'!AL39) + 6) -> 46190 | AZ2: =変更来歴!AX2 -> IMWF-53
A3: =変更来歴!A3 -> 画面設計書 | I3: 内容 | M3: =RIGHT(CELL("filename",A1),LEN(CELL("filename",A1))-FIND("]",CELL("filename",A1))) -> 円(コリア原計) | X3: 画面名 | AA3: =MID(CELL("filename"),FIND("]",CELL("filename"))+1,LEN(CELL("filename"))) & "画面" -> 表紙画面 | AS3: Rev | AV3: =INDIRECT("変更来歴!A" & COUNTA(変更来歴!A7:'変更来歴'!A39) + 6) -> dr1.5
A5: ="画面レイアウト"&"("&MID(CELL("filename"),FIND("]",CELL("filename"))+1,LEN(CELL("filename")))&")" -> 画面レイアウト(表紙) | BB5: Rev.
B6: 1 | C6: 2 | D6: 3 | E6: 4 | F6: 5 | G6: 6 | H6: 7 | I6: 8 | J6: 9 | K6: 10 | L6: 11 | M6: 12 | N6: 13 | O6: 14 | P6: 15 | Q6: 16 | R6: 17 | S6: 18 | T6: 19 | U6: 20 | V6: 21 | W6: 22 | X6: 23 | Y6: 24 | Z6: 25 | AA6: 26 | AB6: 27 | AC6: 28 | AD6: 29 | AE6: 30 | AF6: 31 | AG6: 32 | AH6: 33 | AI6: 34 | AJ6: 35 | AK6: 36 | AL6: 37 | AM6: 38 | AN6: 39 | AO6: 40 | AP6: 41 | AQ6: 42 | AR6: 43 | AS6: 44 | AT6: 45 | AU6: 46 | AV6: 47 | AW6: 48 | AX6: 49 | AY6: 50 | AZ6: 51
B7: 単価上申(円販売一般品) | N7: 案件番号： | R7: SA-PR123456
E8: 過去の申請から内容コピー
C10: 起票日 | F10: ： | H10: 2022/09/29
C11: 所属 | F11: ： | H11: ヒロセ電機株式会社/管理本部/ＩＴ統括部/情報システム企画課
C12: 社員番号 | F12: ： | H12: hirose | L12: 氏名 ： | O12: システム担当者
B13: 1 | C13: 2 | D13: 3 | E13: 4 | F13: 5 | G13: 6 | H13: 7 | I13: 8 | J13: 9 | K13: 10 | L13: 11 | M13: 12 | N13: 13 | O13: 14 | P13: 15 | Q13: 16 | R13: 17 | S13: 18 | T13: 19 | U13: 20 | V13: 21 | W13: 22 | X13: 23 | Y13: 24 | Z13: 25 | AA13: 26 | AB13: 27 | AC13: 28 | AD13: 29 | AE13: 30 | AF13: 31 | AG13: 32 | AH13: 33 | AI13: 34 | AJ13: 35 | AK13: 36 | AL13: 37 | AM13: 38 | AN13: 39 | AO13: 40 | AQ13: 41 | AR13: 42 | AS13: 43 | AT13: 44 | AU13: 45 | AV13: 46 | AW13: 47
B14: 2 | C14: 申請内容
C16: 起票区分 | H16: ◎ 単価上申書
B17: 3 | C17: タイトル*
C18: 得意先コード | T18: 得意先名* | AK18: 客先担当者名
C19: 案件種類* | P19: ▼ | T19: 希望承認期限* | Y19: 2022/9/29
C20: 口銭率 | L20: ☑ 口銭申請有り
B23: 2 | C23: プロジェクト情報
C25: 工事金額 | O25: 万円/月 | T25: 継続期間* | AG25: ヵ月 | AK25: 総工事金額 | AX25: 万円
C26: MFC PJ番号 | R26: MFC OPPORTUNITY番号
C27: 大分類* | H27: 大分類A | P27: ▼ | T27: 中分類* | Y27: 中分類B | AG27: ▼ | AK27: 機種* | AP27: 機種A | AX27: ▼
C28: 量産時期* | T28: 平均生産予定数量 | AG28: /月 | AK28: 競合名 | AX28: ▼
C29: 申請理由* | AX29: ▲
AX30: ▼
C31: 値引補填工事 | H31: 値引きしなければならない理由を記載してください | AX31: ▲
AX32: ▼
C33: 備考欄 | AX33: ▲
AX34: ▼
B37: 5 | C37: 精算通貨
C39: レートタイプ* | G39: ○経営計画レート ○ 顧客契約レート ◎ その他のレート
B40: 6 | C40: No | D40: 通貨 | H40: レート
B41: 8 | C41: 1 | D41: USD | H41: 110
B42: 9 | C42: 2 | D42: EUR | H42: 125
B44: 10
B45: 5 | C45: 申請価格入力
D47: 原計タイプ* | H47: ○ 技術原計 ○ PPM原計 ◎ コリア原計
B48: 6 | C48: No | D48: CL | H48: 品名* | N48: 形* | R48: 月間数量* | V48: 原計通貨* | Z48: 純原価 | AD48: 申請通貨* | AH48: 申請価格* | AL48: 従来価格* | AP48: 物流コスト率% | AT48: 販社売価 | AX48: 代理店売価 | BB48: 得意先要求 | BF48: ピン@FOB | BJ48: 競合名 | BN48: 備考
B49: 7 | AT49: (外貨) | AX49: (外貨) | BB49: 価格 | BF49: 価格基準
B50: 8 | C50: 1 | D50: 4800215830 | H50: TF38-20S-0.5SV(830) | N50: KFH | Q50: ▼ | R50: 70000 | V50: USD | Y50: ▼ | Z50: 0.0673 | AD50: USD | AG50: ▼ | AH50: 0.1211 | AP50: 0.01 | AT50: 0.1359 | AX50: 0.151 | BB50: 0.151 | BF50: 0.0061
B51: 9 | C51: 2 | Q51: ▼ | Y51: ▼ | AG51: ▼
B52: 10
B53: 11
B54: 12
B55: 13
B56: 14
B57: 15 | C57: ＋ 追加 ← 挿入 － 削除 ↑ 上へ ↓ 下へ
B58: 16
B59: 17
B61: 18
B62: 20 | C62: 承認者確認用 | AV62: 通貨：JPY
B64: 21 | C64: No | D64: 形 | F64: CL | J64: 品名 | P64: 原計タイプ | T64: 数量pcs/月 | X64: 純原価 | AB64: 得意先要求価格 | AG64: 従来価格 | AK64: 申請価格 | AO64: 総連結利益率 | AS64: 値引き率 | AW64: 代理店売価 | BA64: 代理店粗利率 | BE64: ピン@ | BH64: 競合名 | BL64: 備考
B65: 22 | C65: 1 | D65: =N50 -> KFH | F65: =D50 -> 4800215830 | J65: =H50 -> TF38-20S-0.5SV(830) | P65: コリア術原計 | T65: =R50 -> 70000 | X65: =SUM(Z50:AC51) -> 0.0673 | AB65: =BB50 -> 0.151 | AG65: =AL50 -> 0 | AK65: =AH50 -> 0.1211 | AO65: =1-Z50/AT50 -> 0.50478293 | AS65: =IFERROR((AK65-AG65)/AG65,"") | AW65: =AX50 -> 0.151 | BA65: =1-(AH50/AX50) -> 0.19801325 | BE65: =BF50 -> 0.0061
B66: 23 | C66: 2
B67: 20 | C67: 形小計
B68: 24 | D68: 形 | F68: 表示通貨 | T68: 売上 | X68: 純原価合計 | AG68: 連結粗利額 | AK68: 連結粗利率 | AO68: 値引き率 | AS68: 値引き額
B69: 25 | C69: 1 | D69: KFH | F69: USD | T69: =SUMPRODUCT($T$65:$W$66,$AK$65:$AN$66) -> 8477 | X69: =SUMPRODUCT(R46:U47,Z46:AC47) -> 0 | AG69: =$T69-$X69 -> 8477 | AK69: =AG69/T69 -> 1 | AO69: =IFERROR(AS69/($T69-AS69),"") -> -0.5 | AS69: =$T$65*($AG$65-$AK$65)+$T$66*($AG$66-$AK$66) -> -8477
B70: 25 | C70: 2 | D70: KFH | F70: JPY | T70: =SUMPRODUCT($T$65:$W$66,$AK$65:$AN$66) -> 8477 | X70: =SUMPRODUCT(R47:U48,Z47:AC48) -> 0 | AG70: =$T70-$X70 -> 8477 | AK70: =AG70/T70 -> 1 | AO70: =IFERROR(AS70/($T70-AS70),"") -> -0.5 | AS70: =$T$65*($AG$65-$AK$65)+$T$66*($AG$66-$AK$66) -> -8477
B71: 20 | C71: 総合計
B72: 24 | F72: 表示通貨 | T72: 売上 | X72: 純原価合計 | AG72: 連結粗利額 | AK72: 連結粗利率 | AO72: 値引き率 | AS72: 値引き額
B73: 25 | F73: USD | T73: =SUMPRODUCT($T$65:$W$66,$AK$65:$AN$66) -> 8477 | X73: =SUMPRODUCT(R49:U50,Z49:AC50) -> 4711 | AG73: =$T73-$X73 -> 3766 | AK73: =AG73/T73 -> 0.44426094 | AO73: =IFERROR(AS73/($T73-AS73),"") -> -0.5 | AS73: =$T$65*($AG$65-$AK$65)+$T$66*($AG$66-$AK$66) -> -8477
B74: 25 | F74: JPY | T74: =SUMPRODUCT($T$65:$W$66,$AK$65:$AN$66) -> 8477 | X74: =SUMPRODUCT(R50:U51,Z50:AC51) -> 4711 | AG74: =$T74-$X74 -> 3766 | AK74: =AG74/T74 -> 0.44426094 | AO74: =IFERROR(AS74/($T74-AS74),"") -> -0.5 | AS74: =$T$65*($AG$65-$AK$65)+$T$66*($AG$66-$AK$66) -> -8477
B75: 26
B76: 27
B77: 28
B78: 29
B80: 31
C81: 添付書類
D84: ファイル名 | R84: サイズ | V84: クリア
D85: ファイル001.xlsx | R85: 102 KB
B87: 34
B88: 35 | C88: 承認者設定
B89: 35 | D89: 承認ルートは必要に応じて、「承認者の追加」をクリックして入力欄を増やしてください。 設定した承認ルートは、設定した承認者の上から順に回送されます。 最終承認者は、一番下に設定してください。
B90: 35
D92: 承認者* | H92: 10637000 | P92: ▼ | R92: 古川 福待 | AB92: コメント
H93: ヒロセ電機株式会社/管理本部/ＩＴ統括部/情報システム企画課
B96: 35 | C96: ＋ 承認者の追加
D98: 承認者* | H98: 10347008 | P98: ▼ | R98: 関 博一 | W98: 部長 | AB98: コメント入力
H99: ヒロセ電機株式会社/管理本部/ＩＴ統括部
B102: 35 | C102: ＋ 承認者の追加
B103: 35
B104: 35 | C104: 確認者設定
D106: 確認者一覧
H107: 確認者名 | Q107: 部門 | AL107: クリア
H108: 志村 亜里沙 | Q108: ヒロセ電機株式会社/管理本部/ＩＴ統括部/情報システム企画課
H109: 出水 瞳 | Q109: ヒロセ電機株式会社/管理本部/ＩＴ統括部/情報システム企画課
H110: 松澤 朱海 | Q110: ヒロセ電機株式会社/管理本部/ＩＴ統括部/情報システム企画課
B112: 35
B113: 36
B114: 37

Sheet 外貨(PPM)
A1: 文書名： | I1: 顧客名 | M1: =変更来歴!M1 -> ヒロセ電機株式会社 | X1: システム | AA1: =変更来歴!AA1 -> 化学物質データ申請 | AK1: 作成者 | AN1: =変更来歴!AP7 -> 古竹 | AS1: 作成日 | AV1: =変更来歴!AL7 -> 46125 | AZ1: 書類番号
A2: intra-mart Accel Platform | I2: プロジェクト | M2: =変更来歴!M2 -> 新環境証明書システム移行 | AK2: 修正者 | AN2: =INDIRECT("変更来歴!AP" & COUNTA(変更来歴!AP7:'変更来歴'!AP39) + 6) -> 古竹 | AS2: 修正日 | AV2: =INDIRECT("変更来歴!AL" & COUNTA(変更来歴!AL7:'変更来歴'!AL39) + 6) -> 46190 | AZ2: =変更来歴!AX2 -> IMWF-53
A3: =変更来歴!A3 -> 画面設計書 | I3: 内容 | M3: =RIGHT(CELL("filename",A1),LEN(CELL("filename",A1))-FIND("]",CELL("filename",A1))) -> 外貨(PPM) | X3: 画面名 | AA3: =MID(CELL("filename"),FIND("]",CELL("filename"))+1,LEN(CELL("filename"))) & "画面" -> 表紙画面 | AS3: Rev | AV3: =INDIRECT("変更来歴!A" & COUNTA(変更来歴!A7:'変更来歴'!A39) + 6) -> dr1.5
A5: ="画面レイアウト"&"("&MID(CELL("filename"),FIND("]",CELL("filename"))+1,LEN(CELL("filename")))&")" -> 画面レイアウト(表紙) | BB5: Rev.
B6: 1 | C6: 2 | D6: 3 | E6: 4 | F6: 5 | G6: 6 | H6: 7 | I6: 8 | J6: 9 | K6: 10 | L6: 11 | M6: 12 | N6: 13 | O6: 14 | P6: 15 | Q6: 16 | R6: 17 | S6: 18 | T6: 19 | U6: 20 | V6: 21 | W6: 22 | X6: 23 | Y6: 24 | Z6: 25 | AA6: 26 | AB6: 27 | AC6: 28 | AD6: 29 | AE6: 30 | AF6: 31 | AG6: 32 | AH6: 33 | AI6: 34 | AJ6: 35 | AK6: 36 | AL6: 37 | AM6: 38 | AN6: 39 | AO6: 40 | AP6: 41 | AQ6: 42 | AR6: 43 | AS6: 44 | AT6: 45 | AU6: 46 | AV6: 47 | AW6: 48 | AX6: 49 | AY6: 50 | AZ6: 51
B7: 単価上申(外貨販売カスタム品) | O7: 案件番号： | S7: SA-PR123456
E8: 過去の申請から内容コピー
C10: 起票日 | F10: ： | H10: 2022/09/29
C11: 所属 | F11: ： | H11: ヒロセ電機株式会社/管理本部/ＩＴ統括部/情報システム企画課
C12: 社員番号 | F12: ： | H12: hirose | L12: 氏名 ： | O12: システム担当者
B13: 1 | C13: 2 | D13: 3 | E13: 4 | F13: 5 | G13: 6 | H13: 7 | I13: 8 | J13: 9 | K13: 10 | L13: 11 | M13: 12 | N13: 13 | O13: 14 | P13: 15 | Q13: 16 | R13: 17 | S13: 18 | T13: 19 | U13: 20 | V13: 21 | W13: 22 | X13: 23 | Y13: 24 | Z13: 25 | AA13: 26 | AB13: 27 | AC13: 28 | AD13: 29 | AE13: 30 | AF13: 31 | AG13: 32 | AH13: 33 | AI13: 34 | AJ13: 35 | AK13: 36 | AL13: 37 | AM13: 38 | AN13: 39 | AO13: 40 | AQ13: 41 | AR13: 42 | AS13: 43 | AT13: 44 | AU13: 45 | AV13: 46 | AW13: 47
B14: 2 | C14: 申請内容
C16: 起票区分 | H16: ◎ 単価上申書
B17: 3 | C17: タイトル*
C18: 得意先コード | T18: 得意先名* | AK18: 客先担当者名
C19: 案件種類* | P19: ▼ | T19: 希望承認期限* | Y19: 2022/9/29
C20: 口銭率 | K20: 0.05 | L20: ☑ 口銭申請有り
B23: 2 | C23: プロジェクト情報
C25: 工事金額 | O25: 万円/月 | T25: 継続期間* | AG25: ヵ月 | AK25: 総工事金額 | AX25: 万円
C26: 海外販社 | T26: SFDC工事番号
C27: 大分類 | H27: 大分類A | P27: ▼ | T27: 中分類 | Y27: 中分類B | AG27: ▼
C28: レップ社名 | T28: 量産時期 | AJ28: 用途(アプリケーション)
C29: 競合名 | P29: ▼ | T29: 生産セット台数 | AJ29: プロジェクトピーク金額 | AW29: 円/月
C30: 申請理由* | AX30: ▲
AX31: ▼
C32: 値引補填工事 | H32: 値引きしなければならない理由を記載してください | AX32: ▲
AX33: ▼
C34: 備考欄 | AX34: ▲
AX35: ▼
B38: 2 | C38: カスタム品申請情報
C40: 償却期間* | O40: ヵ月
B42: 4
B43: 5 | C43: 精算通貨
C45: レートタイプ* | G45: ○経営計画レート ○ 顧客契約レート ◎ その他のレート
B46: 6 | C46: No | D46: 通貨 | H46: レート
B47: 8 | C47: 1 | D47: USD | H47: 110
B48: 9 | C48: 2 | D48: EUR | H48: 125
B50: 10
B51: 5 | C51: 申請価格入力
D53: 原計タイプ* | H53: ○ 技術原計 ◎ PPM原計 ○ コリア原計
B54: 6 | C54: No | D54: CL | H54: 品名* | N54: 形* | R54: 月間数量* | V54: 原計通貨* | Z54: PPM直接コスト* | AE54: 申請通貨* | AI54: FOB価格 | AM54: 従来FOB価格* | AQ54: 物流コスト率 | AU54: 販社売価 | AY54: 代理店売価 | BC54: 得意先 | BG54: ピン@FOB | BJ54: 競合名 | BN54: 備考
B55: 7 | AQ55: (%) | AU55: (外貨) | AY55: (外貨) | BC55: 要求価格 | BG55: 価格基準
B56: 8 | C56: 1 | D56: 5802922450 | H56: FH35C-21S-0.3SHW(50) | N56: FH | Q56: ▼ | R56: 2000000 | V56: JPY | Y56: ▼ | Z56: 5.29 | AE56: USD | AH56: ▼ | AI56: 0.0922 | AM56: 0.094 | AQ56: 0.01 | AU56: 0.1012 | AY56: 0.11 | BC56: 0.11 | BG56: =AI56/21 -> 0.0043904762 | BJ56: JAE
B57: 9 | C57: 2 | D57: 5801232050 | H57: FH34SRJ-30S-0.5SH(50) | N57: FH | Q57: ▼ | R57: 20000 | V57: JPY | Y57: ▼ | Z57: 11 | AE57: USD | AH57: ▼ | AI57: 0.1297 | AM57: 0.13 | AQ57: 0.01 | AU57: 0.136 | AY57: 0.156 | BC57: 0.156 | BG57: =AI57/21 -> 0.0061761905 | BJ57: TE
B58: 10
B59: 14
B60: 15 | C60: ＋ 追加 ← 挿入 － 削除 ↑ 上へ ↓ 下へ
C62: 金型 | Z62: 通貨：JPY
B63: 6 | C63: No | D63: 有償or無償* | H63: 個品名称* | N63: 個品実費価格* | T63: 個品販売価格* | Z63: 倍率
B64: 8 | C64: 1 | D64: 有償 | G64: ▼ | H64: 個品A | N64: 5000 | T64: 5000 | Z64: 10
B65: 14
B66: 15 | C66: ＋ 追加 ← 挿入 － 削除 ↑ 上へ ↓ 下へ
C68: 治工具 | Z68: 通貨：JPY
B69: 6 | C69: No | D69: 有償or無償* | H69: 治工具名称* | N69: 治工具実費価格* | T69: 治工具販売価格* | Z69: 倍率
B70: 8 | C70: 1 | D70: 有償 | G70: ▼ | N70: 5000 | T70: 5000 | Z70: 10
B71: 14
B72: 15 | C72: ＋ 追加 ← 挿入 － 削除 ↑ 上へ ↓ 下へ
B73: 16
B74: 17
B76: 18
B77: 20 | C77: 承認者確認用
B79: 21 | C79: No | D79: 形 | F79: CL | J79: 品名 | P79: 原計タイプ | T79: 申請通貨 | X79: 数量pcs/月 | AB79: コスト | AF79: 得意先要求価格 | AK79: 従来FOB価格 | AO79: FOB価格 | AS79: CIF価格 | AW79: 申請価格 | BA79: 国内収益性 | BE79: FOB値引き率 | BI79: 販社売価 | BM79: 販社粗利率 | BQ79: 連結収益性 | BU79: 代理店売価 | BY79: 代理店粗利率 | CC79: ピン@ | CF79: 競合名 | CJ79: 備考
B80: 22 | C80: 1 | D80: =N56 -> FH | F80: =D56 -> 5802922450 | J80: =H56 -> FH35C-21S-0.3SHW(50) | P80: PPM原計 | T80: =AE56 -> USD | X80: =R56 -> 2000000 | AB80: =Z56/111 -> 0.047657658 | AF80: =BC56 -> 0.11 | AK80: =AM56 -> 0.094 | AO80: =AI56 -> 0.0922 | AS80: =AI56/(1-AQ56) -> 0.093131313 | AW80: =AO80-(AS80*$K$20) -> 0.087543434 | BA80: =1-Z56/111/AW80 -> 0.45561129 | BE80: =(AI56-AM56)/AM56 -> -0.019148936 | BI80: =AU56 -> 0.1012 | BM80: =1-AI56/(1-AQ56)/AU56 -> 0.079730107 | BQ80: =1-(Z56/111+AI56*AQ56+AS80*$K$20)/AU56 -> 0.47395036 | BU80: =AY56 -> 0.11 | BY80: =1-AU56/AY56 -> 0.08 | CC80: =BG56 -> 0.0043904762 | CF80: =BJ56 -> JAE
B81: 23 | C81: 2 | D81: =N57 -> FH | F81: =D57 -> 5801232050 | J81: =H57 -> FH34SRJ-30S-0.5SH(50) | P81: PPM原計 | T81: =AE57 -> USD | X81: =R57 -> 20000 | AB81: =Z57/111 -> 0.099099099 | AF81: =BC57 -> 0.156 | AK81: =AM57 -> 0.13 | AO81: =AI57 -> 0.1297 | AS81: =AI57/(1-AQ57) -> 0.1310101 | AW81: =AO81-(AS81*$K$20) -> 0.12314949 | BA81: =1-Z57/111/AW81 -> 0.19529431 | BE81: =(AI57-AM57)/AM57 -> -0.0023076923 | BI81: =AU57 -> 0.136 | BM81: =1-AI57/(1-AQ57)/AU57 -> 0.036690434 | BQ81: =1-(Z57/111+AI57*AQ57+AS81*$K$20)/AU57 -> 0.21362791 | BU81: =AY57 -> 0.156 | BY81: =1-AU57/AY57 -> 0.12820513 | CC81: =BG57 -> 0.0061761905 | CF81: =BJ57 -> TE
B82: 20 | C82: 形小計
B83: 24 | D83: 形 | F83: 表示通貨 | X83: 売上(国内) | AB83: 直接コスト合計 | AF83: 貢献額 | AK83: 国内収益性 | AO83: 値引き率(FOB) | AS83: 値引き額(FOB) | AW83: 値引き前売上 | BA83: 売上(連結) | BE83: 連結収益性
B84: 24 | AW84: (国内)
B85: 25 | C85: 1 | D85: FH | F85: USD | X85: =SUMPRODUCT(X$80:AA$81,AO$80:AR$81) -> 186994 | AB85: =SUMPRODUCT(X$80:AA$81,AB$80:AE$81) -> 97297.297 | AF85: =X$86-AB$86 -> 89696.703 | AK85: =AF85/X85 -> 0.4796769 | AO85: =AS85/AW85 -> -0.018919203 | AS85: =X$80*(AO$80-AK$80)+X$81*(AO$81-AK$81) -> -3606 | AW85: =SUMPRODUCT(X$80:AA$81,AK$80:AN$81) -> 190600 | BA85: =SUMPRODUCT(X$80:AA$81,BI$80:BL$81) -> 205120 | BE85: =1-(AB$91+X$80*(AO$80*AQ$56+AS$80*$K$20)+X$81*(AO$81*AQ$57+AS$81*$K$20))/BA$91 -> 0.47049835
B86: 25 | C86: 2 | D86: FH | F86: JPY | X86: =SUMPRODUCT(X$80:AA$81,AO$80:AR$81) -> 186994 | AB86: =SUMPRODUCT(X$80:AA$81,AB$80:AE$81) -> 97297.297 | AF86: =X$86-AB$86 -> 89696.703 | AK86: =AF86/X86 -> 0.4796769 | AO86: =AS86/AW86 -> -0.018919203 | AS86: =X$80*(AO$80-AK$80)+X$81*(AO$81-AK$81) -> -3606 | AW86: =SUMPRODUCT(X$80:AA$81,AK$80:AN$81) -> 190600 | BA86: =SUMPRODUCT(X$80:AA$81,BI$80:BL$81) -> 205120 | BE86: =1-(AB$91+X$80*(AO$80*AQ$56+AS$80*$K$20)+X$81*(AO$81*AQ$57+AS$81*$K$20))/BA$91 -> 0.47049835
B87: 20 | C87: 総合計
B88: 24 | F88: 表示通貨 | X88: 売上(国内) | AB88: 直接コスト合計 | AF88: 貢献額 | AK88: 国内収益性 | AO88: 値引き率(FOB) | AS88: 値引き額(FOB) | AW88: 値引き前売上 | BA88: 売上(連結) | BE88: 連結収益性
B89: 24 | AW89: (国内)
B90: 25 | F90: USD | X90: =SUMPRODUCT(X$80:AA$81,AO$80:AR$81) -> 186994 | AB90: =SUMPRODUCT(X$80:AA$81,AB$80:AE$81) -> 97297.297 | AF90: =X$91-AB$91 -> 89696.703 | AK90: =AF90/X90 -> 0.4796769 | AO90: =AS90/AW90 -> -0.018919203 | AS90: =X$80*(AO$80-AK$80)+X$81*(AO$81-AK$81) -> -3606 | AW90: =SUMPRODUCT(X$80:AA$81,AK$80:AN$81) -> 190600 | BA90: =SUMPRODUCT(X$80:AA$81,BI$80:BL$81) -> 205120 | BE90: =1-(AB$91+X$80*(AO$80*AQ$56+AS$80*$K$20)+X$81*(AO$81*AQ$57+AS$81*$K$20))/BA$91 -> 0.47049835
B91: 25 | F91: JPY | X91: =SUMPRODUCT(X$80:AA$81,AO$80:AR$81) -> 186994 | AB91: =SUMPRODUCT(X$80:AA$81,AB$80:AE$81) -> 97297.297 | AF91: =X$91-AB$91 -> 89696.703 | AK91: =AF91/X91 -> 0.4796769 | AO91: =AS91/AW91 -> -0.018919203 | AS91: =X$80*(AO$80-AK$80)+X$81*(AO$81-AK$81) -> -3606 | AW91: =SUMPRODUCT(X$80:AA$81,AK$80:AN$81) -> 190600 | BA91: =SUMPRODUCT(X$80:AA$81,BI$80:BL$81) -> 205120 | BE91: =1-(AB$91+X$80*(AO$80*AQ$56+AS$80*$K$20)+X$81*(AO$81*AQ$57+AS$81*$K$20))/BA$91 -> 0.47049835
B92: 28
B93: 29
C94: 金型 | Z94: 通貨：JPY
C95: No | D95: 有償or無償 | H95: 個品名称 | N95: 個品実費価格 | T95: 個品販売価格 | Z95: 倍率
C96: 1 | D96: 無償 | H96: 個品A | N96: 5000 | T96: 5000 | Z96: 10
N97: 5000 | T97: 5000
C99: 治工具 | Z99: 通貨：JPY
C100: No | D100: 有償or無償 | H100: 治工具名称 | N100: 治工具実費価格 | T100: 治工具販売価格 | Z100: 倍率
C101: 1 | D101: 無償 | N101: 5000 | T101: 5000 | Z101: 10
N102: 5000 | T102: 5000
C104: 償却数量
C105: 一個当たりの償却金額 | R105: ※ 得意先一括負担の場合は記載不要
C106: 未償却リスク | H106: 有 | P106: ▼
C108: コメント* | AX108: ▲
AX109: ▼
B114: 31
C115: 添付書類
D118: ファイル名 | R118: サイズ | V118: クリア
D119: ファイル001.xlsx | R119: 102 KB
B121: 35
B122: 35 | C122: 承認者設定
B123: 35 | D123: 承認ルートは必要に応じて、「承認者の追加」をクリックして入力欄を増やしてください。 設定した承認ルートは、設定した承認者の上から順に回送されます。 最終承認者は、一番下に設定してください。
B124: 35
D126: 承認者* | H126: 10637000 | P126: ▼ | R126: 古川 福待 | AB126: コメント
H127: ヒロセ電機株式会社/管理本部/ＩＴ統括部/情報システム企画課
B130: 35 | C130: ＋ 承認者の追加
...

Sheet 外貨(技術原計)
A1: 文書名： | I1: 顧客名 | M1: =変更来歴!M1 -> ヒロセ電機株式会社 | X1: システム | AA1: =変更来歴!AA1 -> 化学物質データ申請 | AK1: 作成者 | AN1: =変更来歴!AP7 -> 古竹 | AS1: 作成日 | AV1: =変更来歴!AL7 -> 46125 | AZ1: 書類番号
A2: intra-mart Accel Platform | I2: プロジェクト | M2: =変更来歴!M2 -> 新環境証明書システム移行 | AK2: 修正者 | AN2: =INDIRECT("変更来歴!AP" & COUNTA(変更来歴!AP7:'変更来歴'!AP39) + 6) -> 古竹 | AS2: 修正日 | AV2: =INDIRECT("変更来歴!AL" & COUNTA(変更来歴!AL7:'変更来歴'!AL39) + 6) -> 46190 | AZ2: =変更来歴!AX2 -> IMWF-53
A3: =変更来歴!A3 -> 画面設計書 | I3: 内容 | M3: =RIGHT(CELL("filename",A1),LEN(CELL("filename",A1))-FIND("]",CELL("filename",A1))) -> 外貨(技術原計) | X3: 画面名 | AA3: =MID(CELL("filename"),FIND("]",CELL("filename"))+1,LEN(CELL("filename"))) & "画面" -> 表紙画面 | AS3: Rev | AV3: =INDIRECT("変更来歴!A" & COUNTA(変更来歴!A7:'変更来歴'!A39) + 6) -> dr1.5
A5: ="画面レイアウト"&"("&MID(CELL("filename"),FIND("]",CELL("filename"))+1,LEN(CELL("filename")))&")" -> 画面レイアウト(表紙) | BB5: Rev.
B6: 1 | C6: 2 | D6: 3 | E6: 4 | F6: 5 | G6: 6 | H6: 7 | I6: 8 | J6: 9 | K6: 10 | L6: 11 | M6: 12 | N6: 13 | O6: 14 | P6: 15 | Q6: 16 | R6: 17 | S6: 18 | T6: 19 | U6: 20 | V6: 21 | W6: 22 | X6: 23 | Y6: 24 | Z6: 25 | AA6: 26 | AB6: 27 | AC6: 28 | AD6: 29 | AE6: 30 | AF6: 31 | AG6: 32 | AH6: 33 | AI6: 34 | AJ6: 35 | AK6: 36 | AL6: 37 | AM6: 38 | AN6: 39 | AO6: 40 | AP6: 41 | AQ6: 42 | AR6: 43 | AS6: 44 | AT6: 45 | AU6: 46 | AV6: 47 | AW6: 48 | AX6: 49 | AY6: 50 | AZ6: 51
B7: 単価上申(円販売一般品) | N7: 案件番号： | R7: SA-PR123456
E8: 過去の申請から内容コピー
C10: 起票日 | F10: ： | H10: 2022/09/29
C11: 所属 | F11: ： | H11: ヒロセ電機株式会社/管理本部/ＩＴ統括部/情報システム企画課
C12: 社員番号 | F12: ： | H12: hirose | L12: 氏名 ： | O12: システム担当者
B13: 1 | C13: 2 | D13: 3 | E13: 4 | F13: 5 | G13: 6 | H13: 7 | I13: 8 | J13: 9 | K13: 10 | L13: 11 | M13: 12 | N13: 13 | O13: 14 | P13: 15 | Q13: 16 | R13: 17 | S13: 18 | T13: 19 | U13: 20 | V13: 21 | W13: 22 | X13: 23 | Y13: 24 | Z13: 25 | AA13: 26 | AB13: 27 | AC13: 28 | AD13: 29 | AE13: 30 | AF13: 31 | AG13: 32 | AH13: 33 | AI13: 34 | AJ13: 35 | AK13: 36 | AL13: 37 | AM13: 38 | AN13: 39 | AO13: 40 | AQ13: 41 | AR13: 42 | AS13: 43 | AT13: 44 | AU13: 45 | AV13: 46 | AW13: 47
B14: 2 | C14: 申請内容
C16: 起票区分 | H16: ◎ 単価上申書
B17: 3 | C17: タイトル*
C18: 得意先コード | T18: 得意先名* | AK18: 客先担当者名
C19: 案件種類* | P19: ▼ | T19: 希望承認期限* | Y19: 2022/9/29
C20: 口銭率 | K20: 0.05 | L20: ☑ 口銭申請有り
B23: 2 | C23: プロジェクト情報
C25: 工事金額 | O25: 万円/月 | T25: 継続期間* | AG25: ヵ月 | AK25: 総工事金額 | AX25: 万円
C26: 海外販社 | T26: SFDC工事番号
C27: 大分類 | H27: 大分類A | P27: ▼ | T27: 中分類 | Y27: 中分類B | AG27: ▼
C28: レップ社名 | T28: 量産時期 | AJ28: 用途(アプリケーション)
C29: 競合名 | P29: ▼ | T29: 生産セット台数 | AJ29: プロジェクトピーク金額 | AW29: 円/月
C30: 申請理由* | AX30: ▲
AX31: ▼
C32: 値引補填工事 | H32: 値引きしなければならない理由を記載してください | AX32: ▲
AX33: ▼
C34: 備考欄 | AX34: ▲
AX35: ▼
B38: 5 | C38: 精算通貨
C40: レートタイプ* | G40: ○経営計画レート ○ 顧客契約レート ◎ その他のレート
B41: 6 | C41: No | D41: 通貨 | H41: レート
B42: 8 | C42: 1 | D42: USD | H42: 110
B43: 9 | C43: 2 | D43: EUR | H43: 125
B45: 10
B46: 5 | C46: 申請価格入力
D48: 原計タイプ* | H48: ◎ 技術原計 ○ PPM原計 ○ コリア原計
B49: 6 | C49: No | D49: CL | H49: 品名* | N49: 形* | R49: 月間数量* | V49: 原計通貨* | Z49: 製造原価* | AE49: 総原価 | AJ49: 申請通貨* | AN49: FOB価格 | AR49: 従来FOB価格* | AV49: 物流コスト率 | AZ49: 販社売価 | BD49: 代理店売価 | BH49: 得意先 | BL49: ピン@FOB | BO49: 競合名 | BS49: 備考
B50: 7 | AV50: (%) | AZ50: (外貨) | BD50: (外貨) | BH50: 要求価格 | BL50: 価格基準
B51: 8 | C51: 1 | D51: 8311308000 | H51: BF4MC-(375161-01) | N51: OPT | Q51: ▼ | R51: 200 | V51: JPY | Y51: ▼ | Z51: 34690.32 | AE51: 46831.94 | AJ51: USD | AM51: ▼ | AN51: 547.1195 | AR51: 560 | AV51: 0.045 | AZ51: 674
B52: 9 | C52: 2 | D52: 8311309000 | H52: BF4MC-(375168-01) | N52: OPT | Q52: ▼ | R52: 200 | V52: JPY | Y52: ▼ | Z52: 11230.49 | AE52: 15161.17 | AJ52: USD | AM52: ▼ | AN52: 177.1239 | AR52: 180 | AV52: 0.045 | AZ52: 218.2
B53: 10
B54: 14
B55: 15 | C55: ＋ 追加 ← 挿入 － 削除 ↑ 上へ ↓ 下へ
B57: 16
B58: 17
B60: 18
B61: 20 | C61: 承認者確認用
B63: 21 | C63: No | D63: 形 | F63: CL | J63: 品名 | P63: 原計タイプ | T63: 申請通貨 | X63: 数量pcs/月 | AB63: コスト | AF63: 得意先要求価格 | AK63: 従来FOB価格 | AO63: FOB価格 | AS63: CIF価格 | AW63: 申請価格 | BA63: 国内収益性 | BE63: FOB値引き率 | BI63: 販社売価 | BM63: 販社粗利率 | BQ63: 連結収益性 | BU63: 代理店売価 | BY63: 代理店粗利率 | CC63: ピン@ | CF63: 競合名 | CJ63: 備考
B64: 22 | C64: 1 | D64: =N51 -> OPT | F64: =D51 -> 8311308000 | J64: =H51 -> BF4MC-(375161-01) | P64: 技術原計 | T64: =AJ51 -> USD | X64: =R51 -> 200 | AB64: =Z51/H42 -> 315.36655 | AF64: =BH51 -> 0 | AK64: =AR51 -> 560 | AO64: =AN51 -> 547.1195 | AS64: =AN51/(1-AV51) -> 572.9 | AW64: =AN51-(AS64*$K$20) -> 518.4745 | BA64: =(AO64-AS64*$K$20-AE51/H42)/(AE51/H42) -> 0.21780552 | BE64: =(AN51-AR51)/AR51 -> -0.023000893 | BI64: =AZ51 -> 674 | BM64: =1-AN51/(1-AV51)/AZ51 -> 0.15 | BQ64: =1-(Z51/H42+AN51*AV51+AS64*$K$20)/AZ51 -> 0.45306836 | BU64: =BD51 -> 0 | BY64: =IFERROR(1-AZ51/BD51,"") | CC64: =BL51 -> 0
B65: 23 | C65: 2 | D65: =N52 -> OPT | F65: =D52 -> 8311309000 | J65: =H52 -> BF4MC-(375168-01) | P65: 技術原計 | T65: =AJ52 -> USD | X65: =R52 -> 200 | AB65: =Z52/H42 -> 102.09536 | AF65: =BH52 -> 0 | AK65: =AR52 -> 180 | AO65: =AN52 -> 177.1239 | AS65: =AN52/(1-AV52) -> 185.47005 | AW65: =AN52-(AS65*$K$20) -> 167.8504 | BA65: =(AO65-AS65*$K$20-AE52/H42)/(AE52/H42) -> 0.21781787 | BE65: =(AN52-AR52)/AR52 -> -0.015978333 | BI65: =AZ52 -> 218.2 | BM65: =1-AN52/(1-AV52)/AZ52 -> 0.14999976 | BQ65: =1-(Z52/H42+AN52*AV52+AS65*$K$20)/AZ52 -> 0.45307314 | BU65: =BD52 -> 0 | BY65: =IFERROR(1-AZ52/BD52,"") | CC65: =BL52 -> 0
B66: 20 | C66: 形小計
B67: 24 | D67: 形 | F67: 表示通貨 | X67: 売上(国内) | AB67: 総原価合計 | AF67: 総原価利益率 | AK67: 国内収益性 | AO67: 値引き率(FOB) | AS67: 値引き額(FOB) | AW67: 値引き前売上 | BA67: 売上(連結) | BE67: 連結収益性
B68: 24 | AW68: (国内) | BE68: (粗利)
B69: 25 | C69: 1 | D69: OPT | F69: USD | X69: =SUMPRODUCT(X$64:AA$65,AO$64:AR$65) -> 144848.68 | AB69: =SUMPRODUCT(R$51:R$52,AE$51:AE$52)/H42 -> 112714.75 | AF69: =X69-AB69 -> 32133.935 | AK69: =AF69/AB69 -> 0.28509078 | AO69: =AS69/(X69-AS69) -> -0.021292703 | AS69: =X$64*(AO$64-AK$64)+X$65*(AO$65-AK$65) -> -3151.32 | AW69: =SUMPRODUCT(X$64:AA$65,AK$64:AN$65) -> 148000 | BA69: =SUMPRODUCT(X$64:AA$65,BI$64:BL$65) -> 178440 | BE69: =1-(SUMPRODUCT(R$51:R$52,Z$51:Z$52)/107+(AN$51*AV$51+AN$51/(1-AV$51)*$K$20)*R$51+(AN$52*AV$52+AN$52/(1-AV$52)*$K$20)*R$52)/BA$75 -> 0.43995079
B70: 25 | C70: 2 | D70: OPT | F70: JPY | X70: =SUMPRODUCT(X$64:AA$65,AO$64:AR$65)*H42 -> 15933355 | AB70: =SUMPRODUCT(R$51:R$52,AE$51:AE$52) -> 12398622 | AF70: =X70-AB70 -> 3534732.8 | AK70: =AF70/AB70 -> 0.28509078 | AO70: =AS70/(X70-AS70) -> -0.00019774221 | AS70: =X$64*(AO$64-AK$64)+X$65*(AO$65-AK$65) -> -3151.32 | AW70: =SUMPRODUCT(X$64:AA$65,AK$64:AN$65) -> 148000 | BA70: =SUMPRODUCT(X$64:AA$65,BI$64:BL$65) -> 178440 | BE70: =1-(SUMPRODUCT(R$51:R$52,Z$51:Z$52)/107+(AN$51*AV$51+AN$51/(1-AV$51)*$K$20)*R$51+(AN$52*AV$52+AN$52/(1-AV$52)*$K$20)*R$52)/BA$75 -> 0.43995079
B71: 20 | C71: 総合計
B72: 24 | F72: 表示通貨 | X72: 売上(国内) | AB72: 総原価合計 | AF72: 総原価利益率 | AK72: 国内収益性 | AO72: 値引き率(FOB) | AS72: 値引き額(FOB) | AW72: 値引き前売上 | BA72: 売上(連結) | BE72: 連結収益性
B73: 24 | AW73: (国内) | BE73: (粗利)
B74: 25 | F74: USD | X74: =SUMPRODUCT(X$64:AA$65,AO$64:AR$65) -> 144848.68 | AB74: =SUMPRODUCT(R$51:R$52,AE$51:AE$52)/107 -> 115874.97 | AF74: =X74-AB74 -> 28973.708 | AK74: =AF74/AB74 -> 0.25004285 | AO74: =AS74/(X74-AS74) -> -0.021292703 | AS74: =X$64*(AO$64-AK$64)+X$65*(AO$65-AK$65) -> -3151.32 | AW74: =SUMPRODUCT(X$64:AA$65,AK$64:AN$65) -> 148000 | BA74: =SUMPRODUCT(X$64:AA$65,BI$64:BL$65) -> 178440 | BE74: =1-(SUMPRODUCT(R$51:R$52,Z$51:Z$52)/107+(AN$51*AV$51+AN$51/(1-AV$51)*$K$20)*R$51+(AN$52*AV$52+AN$52/(1-AV$52)*$K$20)*R$52)/BA$75 -> 0.43995079
B75: 25 | F75: JPY | X75: =SUMPRODUCT(X$64:AA$65,AO$64:AR$65) -> 144848.68 | AB75: =SUMPRODUCT(R$51:R$52,AE$51:AE$52)/107 -> 115874.97 | AF75: =X75-AB75 -> 28973.708 | AK75: =AF75/AB75 -> 0.25004285 | AO75: =AS75/(X75-AS75) -> -0.021292703 | AS75: =X$64*(AO$64-AK$64)+X$65*(AO$65-AK$65) -> -3151.32 | AW75: =SUMPRODUCT(X$64:AA$65,AK$64:AN$65) -> 148000 | BA75: =SUMPRODUCT(X$64:AA$65,BI$64:BL$65) -> 178440 | BE75: =1-(SUMPRODUCT(R$51:R$52,Z$51:Z$52)/107+(AN$51*AV$51+AN$51/(1-AV$51)*$K$20)*R$51+(AN$52*AV$52+AN$52/(1-AV$52)*$K$20)*R$52)/BA$75 -> 0.43995079
B76: 26
B77: 29
B81: 31
C82: 添付書類
D85: ファイル名 | R85: サイズ | V85: クリア
D86: ファイル001.xlsx | R86: 102 KB
B88: 35
B89: 35 | C89: 承認者設定
B90: 35 | D90: 承認ルートは必要に応じて、「承認者の追加」をクリックして入力欄を増やしてください。 設定した承認ルートは、設定した承認者の上から順に回送されます。 最終承認者は、一番下に設定してください。
B91: 35
D93: 承認者* | H93: 10637000 | P93: ▼ | R93: 古川 福待 | AB93: コメント
H94: ヒロセ電機株式会社/管理本部/ＩＴ統括部/情報システム企画課
B97: 35 | C97: ＋ 承認者の追加
D99: 承認者* | H99: 10347008 | P99: ▼ | R99: 関 博一 | W99: 部長 | AB99: コメント入力
H100: ヒロセ電機株式会社/管理本部/ＩＴ統括部
B103: 35 | C103: ＋ 承認者の追加
B104: 35
B105: 35 | C105: 確認者設定
D107: 確認者一覧
H108: 確認者名 | Q108: 部門 | AL108: クリア
H109: 志村 亜里沙 | Q109: ヒロセ電機株式会社/管理本部/ＩＴ統括部/情報システム企画課
H110: 出水 瞳 | Q110: ヒロセ電機株式会社/管理本部/ＩＴ統括部/情報システム企画課
H111: 松澤 朱海 | Q111: ヒロセ電機株式会社/管理本部/ＩＴ統括部/情報システム企画課
B114: 36
B115: 37

Sheet 外貨(コリア原計)
A1: 文書名： | I1: 顧客名 | M1: =変更来歴!M1 -> ヒロセ電機株式会社 | X1: システム | AA1: =変更来歴!AA1 -> 化学物質データ申請 | AK1: 作成者 | AN1: =変更来歴!AP7 -> 古竹 | AS1: 作成日 | AV1: =変更来歴!AL7 -> 46125 | AZ1: 書類番号
A2: intra-mart Accel Platform | I2: プロジェクト | M2: =変更来歴!M2 -> 新環境証明書システム移行 | AK2: 修正者 | AN2: =INDIRECT("変更来歴!AP" & COUNTA(変更来歴!AP7:'変更来歴'!AP39) + 6) -> 古竹 | AS2: 修正日 | AV2: =INDIRECT("変更来歴!AL" & COUNTA(変更来歴!AL7:'変更来歴'!AL39) + 6) -> 46190 | AZ2: =変更来歴!AX2 -> IMWF-53
A3: =変更来歴!A3 -> 画面設計書 | I3: 内容 | M3: =RIGHT(CELL("filename",A1),LEN(CELL("filename",A1))-FIND("]",CELL("filename",A1))) -> 外貨(コリア原計) | X3: 画面名 | AA3: =MID(CELL("filename"),FIND("]",CELL("filename"))+1,LEN(CELL("filename"))) & "画面" -> 表紙画面 | AS3: Rev | AV3: =INDIRECT("変更来歴!A" & COUNTA(変更来歴!A7:'変更来歴'!A39) + 6) -> dr1.5
A5: ="画面レイアウト"&"("&MID(CELL("filename"),FIND("]",CELL("filename"))+1,LEN(CELL("filename")))&")" -> 画面レイアウト(表紙) | BB5: Rev.
B6: 1 | C6: 2 | D6: 3 | E6: 4 | F6: 5 | G6: 6 | H6: 7 | I6: 8 | J6: 9 | K6: 10 | L6: 11 | M6: 12 | N6: 13 | O6: 14 | P6: 15 | Q6: 16 | R6: 17 | S6: 18 | T6: 19 | U6: 20 | V6: 21 | W6: 22 | X6: 23 | Y6: 24 | Z6: 25 | AA6: 26 | AB6: 27 | AC6: 28 | AD6: 29 | AE6: 30 | AF6: 31 | AG6: 32 | AH6: 33 | AI6: 34 | AJ6: 35 | AK6: 36 | AL6: 37 | AM6: 38 | AN6: 39 | AO6: 40 | AP6: 41 | AQ6: 42 | AR6: 43 | AS6: 44 | AT6: 45 | AU6: 46 | AV6: 47 | AW6: 48 | AX6: 49 | AY6: 50 | AZ6: 51
B7: 単価上申(円販売一般品) | N7: 案件番号： | R7: SA-PR123456
E8: 過去の申請から内容コピー
C10: 起票日 | F10: ： | H10: 2022/09/29
C11: 所属 | F11: ： | H11: ヒロセ電機株式会社/管理本部/ＩＴ統括部/情報システム企画課
C12: 社員番号 | F12: ： | H12: hirose | L12: 氏名 ： | O12: システム担当者
B13: 1 | C13: 2 | D13: 3 | E13: 4 | F13: 5 | G13: 6 | H13: 7 | I13: 8 | J13: 9 | K13: 10 | L13: 11 | M13: 12 | N13: 13 | O13: 14 | P13: 15 | Q13: 16 | R13: 17 | S13: 18 | T13: 19 | U13: 20 | V13: 21 | W13: 22 | X13: 23 | Y13: 24 | Z13: 25 | AA13: 26 | AB13: 27 | AC13: 28 | AD13: 29 | AE13: 30 | AF13: 31 | AG13: 32 | AH13: 33 | AI13: 34 | AJ13: 35 | AK13: 36 | AL13: 37 | AM13: 38 | AN13: 39 | AO13: 40 | AQ13: 41 | AR13: 42 | AS13: 43 | AT13: 44 | AU13: 45 | AV13: 46 | AW13: 47
B14: 2 | C14: 申請内容
C16: 起票区分 | H16: ◎ 単価上申書
B17: 3 | C17: タイトル*
C18: 得意先コード | T18: 得意先名* | AK18: 客先担当者名
C19: 案件種類* | P19: ▼ | T19: 希望承認期限* | Y19: 2022/9/29
C20: 口銭率 | K20: 0.05 | L20: ☑ 口銭申請有り
B23: 2 | C23: プロジェクト情報
C25: 工事金額 | O25: 万円/月 | T25: 継続期間* | AG25: ヵ月 | AK25: 総工事金額 | AX25: 万円
C26: 海外販社 | T26: SFDC工事番号
C27: 大分類 | H27: 大分類A | P27: ▼ | T27: 中分類 | Y27: 中分類B | AG27: ▼
C28: レップ社名 | T28: 量産時期 | AJ28: 用途(アプリケーション)
C29: 競合名 | P29: ▼ | T29: 生産セット台数 | AJ29: プロジェクトピーク金額 | AW29: 円/月
C30: 申請理由* | AX30: ▲
AX31: ▼
C32: 値引補填工事 | H32: 値引きしなければならない理由を記載してください | AX32: ▲
AX33: ▼
C34: 備考欄 | AX34: ▲
AX35: ▼
B38: 5 | C38: 精算通貨
C40: レートタイプ* | G40: ○経営計画レート ○ 顧客契約レート ◎ その他のレート
B41: 6 | C41: No | D41: 通貨 | H41: レート
B42: 8 | C42: 1 | D42: USD | H42: 110
B43: 9 | C43: 2 | D43: EUR | H43: 125
B45: 10
B46: 5 | C46: 申請価格入力
D48: 原計タイプ* | H48: ○ 技術原計 ○ PPM原計 ◎ コリア原計
B49: 6 | C49: No | D49: CL | H49: 品名* | N49: 形* | R49: 月間数量* | V49: 原計通貨* | Z49: 純原価 | AE49: 申請通貨* | AI49: FOB価格 | AM49: 従来FOB価格* | AQ49: 物流コスト率 | AU49: 販社売価 | AY49: 代理店売価 | BC49: 得意先 | BG49: ピン@FOB | BJ49: 競合名 | BN49: 備考
B50: 7 | AQ50: (%) | AU50: (外貨) | AY50: (外貨) | BC50: 要求価格 | BG50: 価格基準
B51: 8 | C51: 1 | D51: 4800215830 | H51: TF38-20S-0.5SV(830) | N51: KFH | Q51: ▼ | R51: 70000 | V51: USD | Y51: ▼ | Z51: 0.0673 | AE51: USD | AH51: ▼ | AI51: 0.1211 | AM51: 0.12 | AQ51: 0.01 | AU51: 0.1359 | AY51: 0.151 | BC51: 0.151 | BG51: 0.0061 | BJ51: JAE
B52: 9 | C52: 2 | Q52: ▼ | Y52: ▼ | AH52: ▼
B53: 10
B54: 14
B55: 15 | C55: ＋ 追加 ← 挿入 － 削除 ↑ 上へ ↓ 下へ
B57: 16
B58: 17 | BM58: =1-(0.0673/0.1359) -> 0.50478293
B60: 18
B61: 20 | C61: 承認者確認用
B63: 21 | C63: No | D63: 形 | F63: CL | J63: 品名 | P63: 原計タイプ | T63: 申請通貨 | X63: 数量pcs/月 | AB63: 純原価 | AF63: 得意先要求価格 | AK63: 従来FOB価格 | AO63: FOB価格 | AS63: CIF価格 | AW63: 申請価格 | BA63: FOB値引き率 | BE63: 販社売価 | BI63: 販社粗利率 | BM63: 連結粗利率 | BQ63: 代理店売価 | BU63: 代理店粗利率 | BY63: ピン@ | CB63: 競合名 | CF63: 備考
B64: 22 | C64: 1 | D64: =N51 -> KFH | F64: =D51 -> 4800215830 | J64: =H51 -> TF38-20S-0.5SV(830) | P64: コリア原計 | T64: =AE51 -> USD | X64: =R51 -> 70000 | AB64: =Z51 -> 0.0673 | AF64: =BC51 -> 0.151 | AK64: =AM51 -> 0.12 | AO64: =AI51 -> 0.1211 | AS64: =AI51/(1-AQ51) -> 0.12232323 | AW64: =AO64-(AS64*$K$20) -> 0.11498384 | BA64: =IFERROR((AI51-AM51)/AM51,"") -> 0.0091666667 | BE64: =AU51 -> 0.1359 | BI64: =1-AI51/(1-AQ51)/AU51 -> 0.099902632 | BM64: =1-AB64/BE64 -> 0.50478293 | BQ64: =AY51 -> 0.151 | BU64: =1-AU51/AY51 -> 0.1 | BY64: =BG51 -> 0.0061 | CB64: =BJ51 -> JAE
B65: 20 | C65: 形小計
B66: 24 | D66: 形 | F66: 表示通貨 | X66: 売上(連結) | AB66: 純原価合計 | AF66: 連結粗利額 | AK66: 連結粗利率 | AO66: 値引き率 | AS66: 値引き額
B67: 25 | C67: 1 | D67: KFH | F67: USD | X67: =SUMPRODUCT(X$64:AA$64,BE$64:BH$64) -> 9513 | AB67: =SUMPRODUCT(X$64:AA$64,AB$64:AE$64) -> 4711 | AF67: =X67-AB67 -> 4802 | AK67: =AF67/X67 -> 0.50478293 | AO67: =IFERROR(AS67/(X67-AS67),"") -> 0.1325 | AS67: =X$64*(BE$64-AK$64) -> 1113
B68: 25 | C68: 2 | D68: KFH | F68: JPY | X68: =SUMPRODUCT(X$64:AA$64,BE$64:BH$64) -> 9513 | AB68: =SUMPRODUCT(X$64:AA$64,AB$64:AE$64) -> 4711 | AF68: =X68-AB68 -> 4802 | AK68: =AF68/X68 -> 0.50478293 | AO68: =IFERROR(AS68/(X68-AS68),"") -> 0.1325 | AS68: =X$64*(BE$64-AK$64) -> 1113
B69: 20 | C69: 総合計
B70: 24 | F70: 表示通貨 | X70: 売上(連結) | AB70: 純原価合計 | AF70: 連結粗利額 | AK70: 連結粗利率 | AO70: 値引き率 | AS70: 値引き額
B71: 25 | F71: USD | X71: =SUMPRODUCT(X$64:AA$64,BE$64:BH$64) -> 9513 | AB71: =SUMPRODUCT(X$64:AA$64,AB$64:AE$64) -> 4711 | AF71: =X71-AB71 -> 4802 | AK71: =AF71/X71 -> 0.50478293 | AO71: =IFERROR(AS71/(X71-AS71),"") -> 0.1325 | AS71: =X$64*(BE$64-AK$64) -> 1113
B72: 25 | F72: JPY | X72: =SUMPRODUCT(X$64:AA$64,BE$64:BH$64) -> 9513 | AB72: =SUMPRODUCT(X$64:AA$64,AB$64:AE$64) -> 4711 | AF72: =X72-AB72 -> 4802 | AK72: =AF72/X72 -> 0.50478293 | AO72: =IFERROR(AS72/(X72-AS72),"") -> 0.1325 | AS72: =X$64*(BE$64-AK$64) -> 1113
B73: 26
B77: 31
C78: 添付書類
D81: ファイル名 | R81: サイズ | V81: クリア
D82: ファイル001.xlsx | R82: 102 KB
B84: 35
B85: 35 | C85: 承認者設定
B86: 35 | D86: 承認ルートは必要に応じて、「承認者の追加」をクリックして入力欄を増やしてください。 設定した承認ルートは、設定した承認者の上から順に回送されます。 最終承認者は、一番下に設定してください。
B87: 35
D89: 承認者* | H89: 10637000 | P89: ▼ | R89: 古川 福待 | AB89: コメント
H90: ヒロセ電機株式会社/管理本部/ＩＴ統括部/情報システム企画課
B93: 35 | C93: ＋ 承認者の追加
D95: 承認者* | H95: 10347008 | P95: ▼ | R95: 関 博一 | W95: 部長 | AB95: コメント入力
H96: ヒロセ電機株式会社/管理本部/ＩＴ統括部
B99: 35 | C99: ＋ 承認者の追加
B100: 35
B101: 35 | C101: 確認者設定
D103: 確認者一覧
H104: 確認者名 | Q104: 部門 | AL104: クリア
H105: 志村 亜里沙 | Q105: ヒロセ電機株式会社/管理本部/ＩＴ統括部/情報システム企画課
H106: 出水 瞳 | Q106: ヒロセ電機株式会社/管理本部/ＩＴ統括部/情報システム企画課
H107: 松澤 朱海 | Q107: ヒロセ電機株式会社/管理本部/ＩＴ統括部/情報システム企画課
B110: 36
B111: 37
